Workbook

Sheet Cover
B12: Ticker | C12: HQY
B13: Date | C13: 46004
B14: Current Price | C14: 96.79
B15: Implied Price | C15: 160.60018
B16: Premium (Discount) | C16: 0.6592642
B17: Cost of Equity | C17: 0.050558
B18: Recommendation | C18: BUY

Sheet quarterly IS
B1: Income Statement- USD($) and shares in thousands | C1: Actual
C2: 2020A | D2: 2021 Q1 | E2: 2021 Q2 | F2: 2021 Q3 | G2: 2021 Q4 | H2: 2021A | I2: 2022 Q1 | J2: 2022 Q2 | K2: 2022 Q3 | L2: 2022 Q4 | M2: 2022A | N2: 2023 Q1 | O2: 2023 Q2 | P2: 2023 Q3 | Q2: 2023 Q4 | R2: 2023A | S2: 2024 Q1 | T2: 2024 Q2 | U2: 2024 Q3 | V2: 2024 Q4 | W2: 2024A | X2: 2025Q1 | Y2: 2025Q2 | Z2: 2025Q3
B3: REVENUE
B4: Service Revenue | C4: 430966 | D4: 102534 | E4: 109182 | F4: 102733 | G4: ='annual IS'!D5-SUM('quarterly IS'!D4:F4) -> 112461 | H4: =SUM(D4:G4) -> 426910 | I4: 104348 | J4: 103034 | K4: 108580 | L4: ='annual IS'!E5-SUM('quarterly IS'!I4:K4) -> 136064 | M4: =SUM(I4:L4) -> 452026 | N4: 111073 | O4: 111960 | P4: 114082 | Q4: ='annual IS'!F5-SUM('quarterly IS'!N4:P4) -> 118575 | R4: =SUM(N4:Q4) -> 455690 | S4: 118214 | T4: 116720 | U4: 119174 | V4: ='annual IS'!G5-SUM('quarterly IS'!S4:U4) -> 124209 | W4: =SUM(S4:V4) -> 478317 | X4: 119785 | Y4: 117873 | Z4: 120286
B5: Custodial Revenue | C5: 190933 | D5: 46978 | E5: 48776 | F5: 49006 | G5: ='annual IS'!D6-SUM('quarterly IS'!D5:F5) -> 58057 | H5: =SUM(D5:G5) -> 202817 | I5: 59365 | J5: 65599 | K5: 74642 | L5: ='annual IS'!E6-SUM('quarterly IS'!I5:K5) -> 61676 | M5: =SUM(I5:L5) -> 261282 | N5: 88480 | O5: 92676 | P5: 100005 | Q5: ='annual IS'!F6-SUM('quarterly IS'!N5:P5) -> 105433 | R5: =SUM(N5:Q5) -> 386594 | S5: 121644 | T5: 138684 | U5: 140953 | V5: ='annual IS'!G6-SUM('quarterly IS'!S5:U5) -> 144133 | W5: =SUM(S5:V5) -> 545414 | X5: 156455 | Y5: 159876 | Z5: 159067
B6: Interchange Revenue | C6: 111671 | D6: 34690 | E6: 31145 | F6: 28215 | G6: ='annual IS'!D7-SUM('quarterly IS'!D6:F6) -> 32779 | H6: =SUM(D6:G6) -> 126829 | I6: 41966 | J6: 37509 | K6: 32864 | L6: ='annual IS'!E7-SUM('quarterly IS'!I6:K6) -> 36101 | M6: =SUM(I6:L6) -> 148440 | N6: 44879 | O6: 38913 | P6: 35132 | Q6: ='annual IS'!F7-SUM('quarterly IS'!N6:P6) -> 38379 | R6: =SUM(N6:Q6) -> 157303 | S6: 47739 | T6: 44524 | U6: 40305 | V6: ='annual IS'!G7-SUM('quarterly IS'!S6:U6) -> 43475 | W6: =SUM(S6:V6) -> 176043 | X6: 54605 | Y6: 48086 | Z6: 42811
A7: x | B7: Total revenue | C7: 733570 | D7: =SUM(D4:D6) -> 184202 | E7: =SUM(E4:E6) -> 189103 | F7: =SUM(F4:F6) -> 179954 | G7: =SUM(G4:G6) -> 203297 | H7: =SUM(H4:H6) -> 756556 | I7: =SUM(I4:I6) -> 205679 | J7: =SUM(J4:J6) -> 206142 | K7: =SUM(K4:K6) -> 216086 | ... Z7: =SUM(Z4:Z6) -> 322164
B8: Revenue Growth (Q/Q) | E8: =(E7-D7)/D7 -> 0.02660666 | F8: =(F7-E7)/E7 -> -0.048381041 | G8: =(G7-F7)/F7 -> 0.12971648 | H8: =(H7-C7)/C7 -> 0.031334433 | I8: =(I7-D7)/D7 -> 0.11659483 | J8: =(J7-E7)/E7 -> 0.090104335 | K8: =(K7-F7)/F7 -> 0.20078464 | L8: =(L7-G7)/G7 -> 0.15024324 | M8: =(M7-H7)/H7 -> 0.1390406 | N8: =(N7-I7)/I7 -> 0.18841496 | O8: =(O7-J7)/J7 -> 0.18146229 | ... W8: =(W7-R7)/R7 -> 0.20026971 | X8: =(X7-V7)/V7 -> 0.061022972 | Y8: =(Y7-X7)/X7 -> -0.015143043 | Z8: =(Z7-Y7)/Y7 -> -0.011266439
B10: COGS
B11: Service Costs | C11: 280214 | D11: 70632 | E11: 67334 | F11: 66217 | G11: ='annual IS'!D12-SUM('quarterly IS'!D11:F11) -> 86119 | H11: =SUM(D11:G11) -> 290302 | I11: 80874 | J11: 74914 | K11: 76493 | L11: ='annual IS'!E12-SUM('quarterly IS'!I11:K11) -> 86235 | M11: =SUM(I11:L11) -> 318516 | N11: 80873 | O11: 76904 | P11: 75721 | Q11: ='annual IS'!F12-SUM('quarterly IS'!N11:P11) -> 83859 | R11: =SUM(N11:Q11) -> 317357 | S11: 82347 | T11: 76915 | U11: 86860 | V11: ='annual IS'!G12-SUM('quarterly IS'!S11:U11) -> 105466 | W11: =SUM(S11:V11) -> 351588 | X11: 88005 | Y11: 75156 | Z11: 76889
B12: Custodial Costs | C12: 19574 | D12: 5009 | E12: 4824 | F12: 5734 | G12: ='annual IS'!D13-SUM('quarterly IS'!D12:F12) -> 6300 | H12: =SUM(D12:G12) -> 21867 | I12: 6641 | J12: 7090 | K12: 6812 | L12: ='annual IS'!E13-SUM('quarterly IS'!I12:K12) -> 5558 | M12: =SUM(I12:L12) -> 26101 | N12: 8038 | O12: 8037 | P12: 8029 | Q12: ='annual IS'!F13-SUM('quarterly IS'!N12:P12) -> 8398 | R12: =SUM(N12:Q12) -> 32502 | S12: 9057 | T12: 10108 | U12: 10241 | V12: ='annual IS'!G13-SUM('quarterly IS'!S12:U12) -> 10269 | W12: =SUM(S12:V12) -> 39675 | X12: 10747 | Y12: 11137 | Z12: 10879
B13: Interchange Costs | C13: 18448 | D13: 5445 | E13: 4974 | F13: 4683 | G13: ='annual IS'!D14-SUM('quarterly IS'!D13:F13) -> 5579 | H13: =SUM(D13:G13) -> 20681 | I13: 6991 | J13: 6326 | K13: 5923 | L13: ='annual IS'!E14-SUM('quarterly IS'!I13:K13) -> 5956 | M13: =SUM(I13:L13) -> 25196 | N13: 7051 | O13: 6943 | P13: 6287 | Q13: ='annual IS'!F14-SUM('quarterly IS'!N13:P13) -> 6810 | R13: =SUM(N13:Q13) -> 27091 | S13: 9055 | T13: 8853 | U13: 6305 | V13: ='annual IS'!G14-SUM('quarterly IS'!S13:U13) -> 7039 | W13: =SUM(S13:V13) -> 31252 | X13: 7781 | Y13: 6947 | Z13: 6333
B14: Total COGS | C14: =SUM(C11:C13) -> 318236 | D14: =SUM(D11:D13) -> 81086 | E14: =SUM(E11:E13) -> 77132 | F14: =SUM(F11:F13) -> 76634 | G14: =SUM(G11:G13) -> 97998 | H14: =SUM(H11:H13) -> 332850 | I14: =SUM(I11:I13) -> 94506 | J14: =SUM(J11:J13) -> 88330 | ... Z14: =SUM(Z11:Z13) -> 94101
A15: x | B15: Gross profit | C15: =C7-C14 -> 415334 | D15: =D7-D14 -> 103116 | E15: =E7-E14 -> 111971 | F15: =F7-F14 -> 103320 | G15: =G7-G14 -> 105299 | H15: =H7-H14 -> 423706 | I15: =I7-I14 -> 111173 | J15: =J7-J14 -> 117812 | ... Z15: =Z7-Z14 -> 228063
B16: Gross profit margin | C16: =C15/C7 -> 0.56618182 | D16: =D15/D7 -> 0.55979848 | E16: =E15/E7 -> 0.59211647 | F16: =F15/F7 -> 0.57414673 | G16: =G15/G7 -> 0.51795649 | H16: =H15/H7 -> 0.56004579 | I16: =I15/I7 -> 0.54051702 | J16: =J15/J7 -> 0.57150896 | ... Z16: =Z15/Z7 -> 0.70790964
B17: Gross profit margin growth | E17: =(E16-D16)/D16 -> 0.05773146 | F17: =(F16-E16)/E16 -> -0.030348319 | G17: =(G16-F16)/F16 -> -0.097867386 | H17: =(H16-C16)/C16 -> -0.010837573 | I17: =(I16-D16)/D16 -> -0.034443578 | J17: =(J16-E16)/E16 -> -0.034803129 | K17: =(K16-F16)/F16 -> 0.02251182 | L17: =(L16-G16)/G16 -> 0.12361793 | M17: =(M16-H16)/H16 -> 0.019304413 | N17: =(N16-I16)/I16 -> 0.12375406 | O17: =(O16-J16)/J16 -> 0.089622281 | ... W17: =(W16-R16)/R16 -> 0.040044658 | X17: =(X16-V16)/V16 -> 0.11832265 | Y17: =(Y16-X16)/X16 -> 0.0528699 | Z17: =(Z16-Y16)/Y16 -> -0.0083117166
B18: OPERATING EXPENSES
B19: Sales and marketing | C19: 49964 | D19: 14086 | E19: 15476 | F19: 12726 | G19: ='annual IS'!D20-SUM('quarterly IS'!D19:F19) -> 16317 | H19: =SUM(D19:G19) -> 58605 | I19: 16560 | J19: 15843 | K19: 17245 | L19: ='annual IS'!E20-SUM('quarterly IS'!I19:K19) -> 19201 | M19: =SUM(I19:L19) -> 68849 | N19: 19935 | O19: 19123 | P19: 19656 | Q19: ='annual IS'!F20-SUM('quarterly IS'!N19:P19) -> 20559 | R19: =SUM(N19:Q19) -> 79273 | S19: 23494 | T19: 21525 | U19: 22636 | V19: ='annual IS'!G20-SUM('quarterly IS'!S19:U19) -> 23084 | W19: =SUM(S19:V19) -> 90739 | X19: 25984 | Y19: 19922 | Z19: 24411
B20: Technology and development | C20: 124809 | D20: 35469 | E20: 37898 | F20: 38070 | G20: ='annual IS'!D21-SUM('quarterly IS'!D20:F20) -> 45927 | H20: =SUM(D20:G20) -> 157364 | I20: 45183 | J20: 46580 | K20: 48890 | L20: ='annual IS'!E21-SUM('quarterly IS'!I20:K20) -> 52722 | M20: =SUM(I20:L20) -> 193375 | N20: 53192 | O20: 54767 | P20: 55614 | Q20: ='annual IS'!F21-SUM('quarterly IS'!N20:P20) -> 55238 | R20: =SUM(N20:Q20) -> 218811 | S20: 56090 | T20: 58580 | U20: 60189 | V20: ='annual IS'!G21-SUM('quarterly IS'!S20:U20) -> 64654 | W20: =SUM(S20:V20) -> 239513 | X20: 61436 | Y20: 64804 | Z20: 65916
B21: General and administrative | C21: 84493 | D21: 20687 | E21: 22812 | F21: 20004 | G21: ='annual IS'!D22-SUM('quarterly IS'!D21:F21) -> 20876 | H21: =SUM(D21:G21) -> 84379 | I21: 23727 | J21: 25937 | K21: 25131 | L21: ='annual IS'!E22-SUM('quarterly IS'!I21:K21) -> 22677 | M21: =SUM(I21:L21) -> 97472 | N21: 25538 | O21: 27825 | P21: 27153 | Q21: ='annual IS'!F22-SUM('quarterly IS'!N21:P21) -> 23140 | R21: =SUM(N21:Q21) -> 103656 | S21: 38236 | T21: 32260 | U21: 31789 | V21: ='annual IS'!G22-SUM('quarterly IS'!S21:U21) -> 29975 | W21: =SUM(S21:V21) -> 132260 | X21: 25536 | Y21: 29990 | Z21: 30880
B22: Amortization of acquired intangible assets | C22: 76064 | D22: 19814 | E22: 20289 | F22: 19642 | G22: ='annual IS'!D23-SUM('quarterly IS'!D22:F22) -> 23046 | H22: =SUM(D22:G22) -> 82791 | I22: 23698 | J22: 24181 | K22: 23541 | L22: ='annual IS'!E23-SUM('quarterly IS'!I22:K22) -> 23166 | M22: =SUM(I22:L22) -> 94586 | N22: 23166 | O22: 23166 | P22: 23213 | Q22: ='annual IS'!F23-SUM('quarterly IS'!N22:P22) -> 23218 | R22: =SUM(N22:Q22) -> 92763 | S22: 25545 | T22: 30981 | U22: 28350 | V22: ='annual IS'!G23-SUM('quarterly IS'!S22:U22) -> 27002 | W22: =SUM(S22:V22) -> 111878 | X22: 27002 | Y22: 27001 | Z22: 27002
B23: Merger Integration | C23: 45990 | D23: 8807 | E23: 16371 | F23: 13244 | G23: ='annual IS'!D24-SUM('quarterly IS'!D23:F23) -> 26383 | H23: =SUM(D23:G23) -> 64805 | I23: 9294 | J23: 7683 | K23: 6509 | L23: ='annual IS'!E24-SUM('quarterly IS'!I23:K23) -> 5110 | M23: =SUM(I23:L23) -> 28596 | N23: 3458 | O23: 2044 | P23: 2655 | Q23: ='annual IS'!F24-SUM('quarterly IS'!N23:P23) -> 2278 | R23: =SUM(N23:Q23) -> 10435 | S23: 2143 | T23: 1777 | U23: 34437 | V23: ='annual IS'!G24-SUM('quarterly IS'!S23:U23) -> 2178 | W23: =SUM(S23:V23) -> 40535 | X23: 1275 | Y23: 1266 | Z23: 1159
B24: Total Operating Expense | C24: =SUM(C19:C23) -> 381320 | D24: =SUM(D19:D23) -> 98863 | E24: =SUM(E19:E23) -> 112846 | F24: =SUM(F19:F23) -> 103686 | G24: =SUM(G19:G23) -> 132549 | H24: =SUM(H19:H23) -> 447944 | I24: =SUM(I19:I23) -> 118462 | J24: =SUM(J19:J23) -> 120224 | ... Z24: =SUM(Z19:Z23) -> 149368
B25: OpEx Growth | E25: =(E24-D24)/D24 -> 0.14143815 | F25: =(F24-E24)/E24 -> -0.081172571 | G25: =(G24-F24)/F24 -> 0.27836931 | H25: =(H24-C24)/C24 -> 0.1747194 | I25: =(I24-D24)/D24 -> 0.19824403 | J25: =(J24-E24)/E24 -> 0.065381139 | K25: =(K24-F24)/F24 -> 0.1700326 | L25: =(L24-G24)/G24 -> -0.072976786 | M25: =(M24-H24)/H24 -> 0.077987427 | N25: =(N24-I24)/I24 -> 0.057630295 | O25: =(O24-J24)/J24 -> 0.055737623 | ... W25: =(W24-R24)/R24 -> 0.21782278 | X25: =(X24-146893)/146893 -> -0.038531448 | Y25: =(Y24-X24)/X24 -> 0.012390872 | Z25: =(Z24-Y24)/Y24 -> 0.044655658
A26: x | B26: EBIT | C26: =C15-C24 -> 34014 | D26: =D15-D24 -> 4253 | E26: =E15-E24 -> -875 | F26: =F15-F24 -> -366 | G26: =G15-G24 -> -27250 | H26: =H15-H24 -> -24238 | I26: =I15-I24 -> -7289 | J26: =J15-J24 -> -2412 | ... Z26: =Z15-Z24 -> 78695
B27: EBIT Margin | C27: =C26/C7 -> 0.046367763 | D27: =D26/D7 -> 0.023088783 | E27: =E26/E7 -> -0.004627108 | F27: =F26/F7 -> -0.0020338531 | G27: =G26/G7 -> -0.13404034 | H27: =H26/H7 -> -0.032037285 | I27: =I26/I7 -> -0.035438718 | J27: =J26/J7 -> -0.011700672 | ... Z27: =Z26/Z7 -> 0.24427
B29: OTHER INCOME (EXPENSE)
B30: Interest expense | C30: -34881 | D30: -6689 | E30: -7254 | F30: -11881 | G30: ='annual IS'!D31-SUM('quarterly IS'!D30:F30) -> -10748 | H30: =SUM(D30:G30) -> -36572 | I30: -10461 | J30: -11493 | K30: -12165 | L30: ='annual IS'!E31-SUM('quarterly IS'!I30:K30) -> -14305 | M30: =SUM(I30:L30) -> -48424 | N30: -14997 | O30: -13272 | P30: -13545 | Q30: ='annual IS'!F31-SUM('quarterly IS'!N30:P30) -> -13641 | R30: =SUM(N30:Q30) -> -55455 | S30: -11795 | T30: -15427 | U30: -18155 | V30: ='annual IS'!G31-SUM('quarterly IS'!S30:U30) -> -15257 | W30: =SUM(S30:V30) -> -60634 | X30: -14858 | Y30: -14955 | Z30: -14049
B31: Other income, net | C31: 5007 | D31: -3630 | E31: 344 | F31: 3122 | G31: ='annual IS'!D32-SUM('quarterly IS'!D31:F31) -> -5767 | H31: ='annual IS'!D32 -> -5931 | I31: -301 | J31: 32 | K31: 443 | L31: ='annual IS'!E32-SUM('quarterly IS'!I31:K31) -> 1097 | M31: =SUM(I31:L31) -> 1271 | N31: 1828 | O31: 2756 | P31: 3741 | Q31: ='annual IS'!F32-SUM('quarterly IS'!N31:P31) -> 4471 | R31: =SUM(N31:Q31) -> 12796 | S31: 3404 | T31: 3114 | U31: 4748 | V31: ='annual IS'!G32-SUM('quarterly IS'!S31:U31) -> 3068 | W31: =SUM(S31:V31) -> 14334 | X31: 2733 | Y31: 3391 | Z31: 2886
B32: Total other expense | C32: =SUM(C30:C31) -> -29874 | D32: =SUM(D30:D31) -> -10319 | E32: =SUM(E30:E31) -> -6910 | F32: =SUM(F30:F31) -> -8759 | G32: =SUM(G30:G31) -> -16515 | H32: =SUM(H30:H31) -> -42503 | I32: =SUM(I30:I31) -> -10762 | J32: =SUM(J30:J31) -> -11461 | ... Z32: =SUM(Z30:Z31) -> -11163
A33: x | B33: INCOME BEFORE INCOME TAXES (EBT) | C33: =C26+C32 -> 4140 | D33: =D26+D32 -> -6066 | E33: =E26+E32 -> -7785 | F33: =F26+F32 -> -9125 | G33: =G26+G32 -> -43765 | H33: =H26+H32 -> -66741 | I33: =I26+I32 -> -18051 | J33: =J26+J32 -> -13873 | ... Z33: =Z26+Z32 -> 67532
B34: Provision for income taxes (benefit) | C34: -4694 | D34: -3451 | E34: -3967 | F34: -4087 | G34: =SUM('annual IS'!D35-SUM('quarterly IS'!D34:F34)) -> -10947 | H34: -22452 | I34: -4412 | J34: -3219 | K34: -4539 | L34: ='annual IS'!E35-SUM('quarterly IS'!I34:K34) -> 217 | M34: -11953 | N34: 5918 | O34: 3643 | P34: 6414 | Q34: ='annual IS'!F35-SUM('quarterly IS'!N34:P34) -> 3353 | R34: 19328 | S34: 4426 | T34: 10794 | U34: 515 | V34: ='annual IS'!G35-SUM('quarterly IS'!S34:U34) -> 3596 | W34: 19331 | X34: 17038 | Y34: 18194 | Z34: 15840
B35: Effective tax rate | C35: =C34/C33 -> -1.1338164 | D35: =D34/D33 -> 0.56890867 | E35: =E34/E33 -> 0.50956969 | F35: =F34/F33 -> 0.44789041 | G35: =G34/G33 -> 0.25013138 | H35: =H34/H33 -> 0.33640491 | I35: =I34/I33 -> 0.24441859 | J35: =J34/J33 -> 0.23203345 | ... Z35: =Z34/Z33 -> 0.23455547
A37: x | B37: NET INCOME ATTRIBUTABLE TO HQY | C37: =C33-C34 -> 8834 | D37: =D33-D34 -> -2615 | E37: =E33-E34 -> -3818 | F37: =F33-F34 -> -5038 | G37: =G33-G34 -> -32818 | H37: =H33-H34 -> -44289 | I37: =I33-I34 -> -13639 | J37: =J33-J34 -> -10654 | ... Z37: =Z33-Z34 -> 51692
B38: Net Income Margin | C38: =C37/C7 -> 0.012042477 | D38: =D37/D7 -> -0.014196371 | E38: =E37/E7 -> -0.020190055 | F38: =F37/F7 -> -0.027996043 | G38: =G37/G7 -> -0.16142885 | H38: =H37/H7 -> -0.05854028 | I38: =I37/I7 -> -0.066312069 | J38: =J37/J7 -> -0.051682821 | ... Z38: =Z37/Z7 -> 0.16045244
B40: NET INCOME PER COMMON SHARE ATTRIBUTABLE TO HQY:
B41: Basic | C41: 0.12 | D41: -0.03 | E41: -0.05 | F41: -0.06 | G41: =SUM('annual IS'!D42-SUM('quarterly IS'!D41:F41)) -> -0.39 | H41: =SUM(D41:G41) -> -0.53 | I41: -0.16 | J41: -0.13 | K41: -0.02 | L41: ='annual IS'!E42-SUM('quarterly IS'!I41:K41) -> 0 | M41: -0.31 | N41: 0.05 | O41: 0.12 | P41: 0.17 | Q41: ='annual IS'!F42-SUM('quarterly IS'!N41:P41) -> 0.31 | R41: 0.65 | S41: 0.33 | T41: 0.41 | U41: 0.07 | V41: ='annual IS'!G42-SUM('quarterly IS'!S41:U41) -> 0.3 | W41: 1.11 | X41: 0.62 | Y41: 0.69 | Z41: 0.6
B42: Diluted | C42: 0.12 | D42: -0.03 | E42: -0.05 | F42: -0.06 | G42: =SUM('annual IS'!D43-SUM('quarterly IS'!D42:F42)) -> -0.39 | H42: =SUM(D42:G42) -> -0.53 | I42: -0.16 | J42: -0.13 | K42: -0.02 | L42: ='annual IS'!E43-SUM('quarterly IS'!I42:K42) -> 0 | M42: -0.31 | N42: 0.05 | O42: 0.12 | P42: 0.17 | Q42: ='annual IS'!F43-SUM('quarterly IS'!N42:P42) -> 0.3 | R42: 0.64 | S42: 0.33 | T42: 0.4 | U42: 0.06 | V42: ='annual IS'!G43-SUM('quarterly IS'!S42:U42) -> 0.3 | W42: 1.09 | X42: 0.61 | Y42: 0.68 | Z42: 0.59
B44: Shares used in calculation (000’s)
B45: Basic | C45: 74235 | D45: 81747 | E45: 83481 | F45: 83551 | G45: =SUM('annual IS'!D46) -> 83133 | H45: =G45 -> 83133 | I45: 84022 | J45: 84443 | K45: 84572 | L45: ='annual IS'!E46 -> 84442 | M45: =L45 -> 84442 | N45: 85030 | O45: 85533 | P45: 85697 | Q45: ='annual IS'!F46 -> 85564 | R45: =Q45 -> 85564 | S45: 86472 | T45: 87131 | U45: 87193 | V45: ='annual IS'!G46 -> 86870 | W45: =V45 -> 86870 | X45: 86655 | Y45: 86550 | Z45: 85995
B46: Diluted | C46: 75679 | D46: 81747 | E46: 83481 | F46: 83551 | G46: =SUM('annual IS'!D47) -> 83133 | H46: =G46 -> 83133 | I46: 84022 | J46: 84443 | K46: 84572 | L46: ='annual IS'!E47 -> 84442 | M46: =L46 -> 84442 | N46: 86102 | O46: 86341 | P46: 87122 | Q46: ='annual IS'!F47 -> 86957 | R46: =Q46 -> 86957 | S46: 88324 | T46: 88646 | U46: 88634 | V46: ='annual IS'!G47 -> 88828 | W46: =V46 -> 88828 | X46: 88415 | Y46: 87746 | Z46: 86970
B47: Change in diluted shares | H47: =H46-C46 -> 7454 | I47: =I46-G46 -> 889 | J47: =J46-I46 -> 421 | K47: =K46-J46 -> 129 | L47: =L46-K46 -> -130 | M47: =M46-H46 -> 1309 | N47: =N46-L46 -> 1660 | O47: =O46-N46 -> 239 | P47: =P46-O46 -> 781 | Q47: =Q46-P46 -> -165 | R47: =R46-M46 -> 2515 | S47: =S46-Q46 -> 1367 | T47: =T46-S46 -> 322 | U47: =U46-T46 -> -12 | V47: =V46-U46 -> 194 | W47: =W46-R46 -> 1871 | X47: =X46-V46 -> -413 | Y47: =Y46-X46 -> -669 | Z47: =Z46-Y46 -> -776

Sheet annual IS
B2: Income Statement- USD($) and shares in thousands | C2: Actual | H2: Expected
C3: 2020 | D3: =C3+1 -> 2021 | E3: =D3+1 -> 2022 | F3: =E3+1 -> 2023 | G3: =F3+1 -> 2024 | H3: =G3+1 -> 2025 | I3: =H3+1 -> 2026 | J3: =I3+1 -> 2027 | K3: =J3+1 -> 2028 | L3: =K3+1 -> 2029
B4: REVENUE
B5: Service Revenue | C5: 430966 | D5: 426910 | E5: 452026 | F5: 455690 | G5: 478317 | H5: ='Revenue Build'!X3 -> 491352.42 | I5: ='Revenue Build'!Y3 -> 505600.02 | J5: ='Revenue Build'!Z3 -> 522131.77 | K5: ='Revenue Build'!AA3 -> 539980.28 | L5: ='Revenue Build'!AB3 -> 559558.64
B6: Custodial Revenue | C6: 190933 | D6: 202817 | E6: 261282 | F6: 386594 | G6: 545414 | H6: ='Revenue Build'!X4 -> 662102.22 | I6: ='Revenue Build'!Y4 -> 750965.44 | J6: ='Revenue Build'!Z4 -> 838801.15 | K6: ='Revenue Build'!AA4 -> 893208.91 | L6: ='Revenue Build'!AB4 -> 951582.23
B7: Interchange Revenue | C7: 111671 | D7: 126829 | E7: 148440 | F7: 157303 | G7: 176043 | H7: ='Revenue Build'!X5 -> 185908.66 | I7: ='Revenue Build'!Y5 -> 196655.06 | J7: ='Revenue Build'!Z5 -> 208765 | K7: ='Revenue Build'!AA5 -> 221933.57 | L7: ='Revenue Build'!AB5 -> 236399.35
A8: x | B8: Total revenue | C8: =SUM(C5:C7) -> 733570 | D8: =SUM(D5:D7) -> 756556 | E8: =SUM(E5:E7) -> 861748 | F8: =SUM(F5:F7) -> 999587 | G8: =SUM(G5:G7) -> 1199774 | H8: =SUM(H5:H7) -> 1339363.3 | I8: =SUM(I5:I7) -> 1453220.5 | J8: =SUM(J5:J7) -> 1569697.9 | ... L8: =SUM(L5:L7) -> 1747540.2
B9: Revenue Growth (Y/Y or Q/Q) | D9: =(D8-C8)/C8 -> 0.031334433 | E9: =(E8-D8)/D8 -> 0.1390406 | F9: =(F8-E8)/E8 -> 0.15995279 | G9: =(G8-F8)/F8 -> 0.20026971 | H9: =(H8-G8)/G8 -> 0.11634633 | I9: =(I8-H8)/H8 -> 0.085008475 | J9: =(J8-I8)/I8 -> 0.08015121 | K9: =(K8-J8)/J8 -> 0.054421201 | L9: =(L8-K8)/K8 -> 0.055837225
B11: COGS
B12: Service Costs | C12: 280214 | D12: 290302 | E12: 318516 | F12: 317357 | G12: 351588 | H12: ='Expense Build'!AA5 -> 353773.74 | I12: ='Expense Build'!AB5 -> 369088.02 | J12: ='Expense Build'!AC5 -> 386377.51 | K12: ='Expense Build'!AD5 -> 404985.21 | L12: ='Expense Build'!AE5 -> 425264.57
B13: Custodial Costs | C13: 19574 | D13: 21867 | E13: 26101 | F13: 32502 | G13: 39675 | H13: ='Expense Build'!AA6 -> 48163.24 | I13: ='Expense Build'!AB6 -> 50872.582 | J13: ='Expense Build'!AC6 -> 52628.822 | K13: ='Expense Build'!AD6 -> 51576.479 | L13: ='Expense Build'!AE6 -> 50189.213
B14: Interchange Costs | C14: 18448 | D14: 20681 | E14: 25196 | F14: 27091 | G14: 31252 | H14: ='Expense Build'!AA7 -> 31520.695 | I14: ='Expense Build'!AB7 -> 33342.741 | J14: ='Expense Build'!AC7 -> 35395.973 | K14: ='Expense Build'!AD7 -> 37628.696 | L14: ='Expense Build'!AE7 -> 40081.359
B15: Total COGS | C15: =SUM(C12:C14) -> 318236 | D15: =SUM(D12:D14) -> 332850 | E15: =SUM(E12:E14) -> 369813 | F15: =SUM(F12:F14) -> 376950 | G15: =SUM(G12:G14) -> 422515 | H15: =SUM(H12:H14) -> 433457.68 | I15: =SUM(I12:I14) -> 453303.34 | J15: =SUM(J12:J14) -> 474402.3 | ... L15: =SUM(L12:L14) -> 515535.14
A16: x | B16: Gross profit | C16: =C8-C15 -> 415334 | D16: =D8-D15 -> 423706 | E16: =E8-E15 -> 491935 | F16: =F8-F15 -> 622637 | G16: =G8-G15 -> 777259 | H16: =H8-H15 -> 905905.62 | I16: =I8-I15 -> 999917.19 | J16: =J8-J15 -> 1095295.6 | ... L16: =L8-L15 -> 1232005.1
B17: Gross profit margin | C17: =C16/C8 -> 0.56618182 | D17: =D16/D8 -> 0.56004579 | E17: =E16/E8 -> 0.57085714 | F17: =F16/F8 -> 0.62289426 | G17: =G16/G8 -> 0.64783784 | H17: =H16/H8 -> 0.67637035 | I17: =I16/I8 -> 0.68806982 | J17: =J16/J8 -> 0.69777478 | ... L17: =L16/L8 -> 0.70499383
B19: OPERATING EXPENSES
B20: Sales and marketing | C20: 49964 | D20: 58605 | E20: 68849 | F20: 79273 | G20: 90739 | H20: ='Expense Build'!AA10 -> 101899.84 | I20: ='Expense Build'!AB10 -> 110562.19 | J20: ='Expense Build'!AC10 -> 119423.88 | K20: ='Expense Build'!AD10 -> 125923.07 | L20: ='Expense Build'!AE10 -> 132954.27
B21: Technology and development | C21: 124809 | D21: 157364 | E21: 193375 | F21: 218811 | G21: 239513 | H21: ='Expense Build'!AA11 -> 273517.1 | I21: ='Expense Build'!AB11 -> 296768.37 | J21: ='Expense Build'!AC11 -> 320554.72 | K21: ='Expense Build'!AD11 -> 337999.69 | L21: ='Expense Build'!AE11 -> 356872.66
B22: General and administrative | C22: 84493 | D22: 84379 | E22: 97472 | F22: 103656 | G22: 132260 | H22: ='Expense Build'!AA12 -> 148336.32 | I22: ='Expense Build'!AB12 -> 160946.17 | J22: ='Expense Build'!AC12 -> 173846.19 | K22: ='Expense Build'!AD12 -> 183307.11 | L22: ='Expense Build'!AE12 -> 193542.47
B23: Amortization of acquired intangible assets | C23: 76064 | D23: 82791 | E23: 94586 | F23: 92763 | G23: 111878 | H23: ='Expense Build'!AA13 -> 136329.18 | I23: ='Expense Build'!AB13 -> 147918.31 | J23: ='Expense Build'!AC13 -> 159774.14 | K23: ='Expense Build'!AD13 -> 168469.24 | L23: ='Expense Build'!AE13 -> 177876.1
B24: Merger Integration | C24: 45990 | D24: 64805 | E24: 28596 | F24: 10435 | G24: 40535 | H24: ='Expense Build'!AA14 -> 4710 | I24: ='Expense Build'!AB14 -> 0 | J24: ='Expense Build'!AC14 -> 0 | K24: ='Expense Build'!AD14 -> 0 | L24: ='Expense Build'!AE14 -> 0
B25: Total Operating Expense | C25: =SUM(C20:C24) -> 381320 | D25: =SUM(D20:D24) -> 447944 | E25: =SUM(E20:E24) -> 482878 | F25: =SUM(F20:F24) -> 504938 | G25: =SUM(G20:G24) -> 614925 | H25: =SUM(H20:H24) -> 664792.44 | I25: =SUM(I20:I24) -> 716195.04 | J25: =SUM(J20:J24) -> 773598.94 | ... L25: =SUM(L20:L24) -> 861245.5
B26: OpEx Growth | D26: =(D25-C25)/C25 -> 0.1747194 | E26: =(E25-D25)/D25 -> 0.077987427 | F26: =(F25-E25)/E25 -> 0.045684417 | G26: =(G25-F25)/F25 -> 0.21782278 | H26: =(H25-G25)/G25 -> 0.081095157 | I26: =(I25-H25)/H25 -> 0.077321279 | J26: =(J25-I25)/I25 -> 0.08015121 | K26: =(K25-J25)/J25 -> 0.054421201 | L26: =(L25-K25)/K25 -> 0.055837225
A27: x | B27: EBIT | C27: =C16-C25 -> 34014 | D27: =D16-D25 -> -24238 | E27: =E16-E25 -> 9057 | F27: =F16-F25 -> 117699 | G27: =G16-G25 -> 162334 | H27: =H16-H25 -> 241113.18 | I27: =I16-I25 -> 283722.15 | J27: =J16-J25 -> 321696.67 | ... L27: =L16-L25 -> 370759.58
B28: EBIT Margin | C28: =C27/C8 -> 0.046367763 | D28: =D27/D8 -> -0.032037285 | E28: =E27/E8 -> 0.010510033 | F28: =F27/F8 -> 0.11774763 | G28: =G27/G8 -> 0.13530382 | H28: =H27/H8 -> 0.18002074 | I28: =I27/I8 -> 0.19523681 | J28: =J27/J8 -> 0.20494177 | ... L28: =L27/L8 -> 0.21216083
B30: OTHER INCOME (EXPENSE)
B31: Interest expense | C31: -34881 | D31: -36572 | E31: -48424 | F31: -55455 | G31: -60634 | H31: ='Expense Build'!AA18 -> -57102.601 | I31: ='Expense Build'!AB18 -> -60516.648 | J31: ='Expense Build'!AC18 -> -63811.542 | K31: ='Expense Build'!AD18 -> -65643.997 | L31: ='Expense Build'!AE18 -> -67577.543
B32: Other income, net | C32: 5007 | D32: -5931 | E32: 1271 | F32: 12796 | G32: 14334 | H32: ='Expense Build'!AA41*'annual IS'!H8 -> 5627.4461 | I32: ='Expense Build'!AB41*'annual IS'!I8 -> 6105.8267 | J32: ='Expense Build'!AC41*'annual IS'!J8 -> 6595.2161 | K32: ='Expense Build'!AD41*'annual IS'!K8 -> 6954.1357 | L32: ='Expense Build'!AE41*'annual IS'!L8 -> 7342.4353
B33: Total other expense | C33: =SUM(C31:C32) -> -29874 | D33: =SUM(D31:D32) -> -42503 | E33: =SUM(E31:E32) -> -47153 | F33: =SUM(F31:F32) -> -42659 | G33: =SUM(G31:G32) -> -46300 | H33: =SUM(H31:H32) -> -51475.155 | I33: =SUM(I31:I32) -> -54410.821 | J33: =SUM(J31:J32) -> -57216.326 | ... L33: =SUM(L31:L32) -> -60235.108
A34: x | B34: INCOME BEFORE INCOME TAXES (EBT) | C34: =C27+C33 -> 4140 | D34: =D27+D33 -> -66741 | E34: =E27+E33 -> -38096 | F34: =F27+F33 -> 75040 | G34: =G27+G33 -> 116034 | H34: =H27+H33 -> 189638.02 | I34: =I27+I33 -> 229311.33 | J34: =J27+J33 -> 264480.34 | ... L34: =L27+L33 -> 310524.47
B35: Provision for income taxes (benefit) | C35: -4694 | D35: -22452 | E35: -11953 | F35: 19328 | G35: 19331 | H35: ='Expense Build'!AA39*'annual IS'!H34 -> 45968.257 | I35: ='Expense Build'!AB39*'annual IS'!I34 -> 57006.796 | J35: ='Expense Build'!AC39*'annual IS'!J34 -> 65591.125 | K35: ='Expense Build'!AD39*'annual IS'!K34 -> 71635.847 | L35: ='Expense Build'!AE39*'annual IS'!L34 -> 77631.118
B36: Effective tax rate | C36: =C35/C34 -> -1.1338164 | D36: =D35/D34 -> 0.33640491 | E36: =E35/E34 -> 0.31375997 | F36: =F35/F34 -> 0.2575693 | G36: =G35/G34 -> 0.16659772 | H36: 0.2424 | I36: 0.2486 | J36: 0.248 | K36: 0.25 | L36: 0.25
A38: x | B38: NET INCOME ATTRIBUTABLE TO HQY | C38: =C34-C35 -> 8834 | D38: =D34-D35 -> -44289 | E38: =E34-E35 -> -26143 | F38: =F34-F35 -> 55712 | G38: =G34-G35 -> 96703 | H38: =H34-H35 -> 143669.77 | I38: =I34-I35 -> 172304.53 | J38: =J34-J35 -> 198889.22 | ... L38: =L34-L35 -> 232893.35
B39: Net Income Margin | C39: =C38/C8 -> 0.012042477 | D39: =D38/D8 -> -0.05854028 | E39: =E38/E8 -> -0.030337175 | F39: =F38/F8 -> 0.055735019 | G39: =G38/G8 -> 0.080601013 | H39: =H38/H8 -> 0.10726721 | I39: =I38/I8 -> 0.11856737 | J39: =J38/J8 -> 0.12670541 | ... L39: =L38/L8 -> 0.13326924
B41: NET INCOME PER COMMON SHARE ATTRIBUTABLE TO HQY:
B42: Basic | C42: 0.12 | D42: -0.53 | E42: -0.31 | F42: 0.65 | G42: 1.11 | H42: =H38/H46 -> 1.6538479 | I42: =I38/I46 -> 1.9834757 | J42: =J38/J46 -> 2.2895041 | K42: =K38/K46 -> 2.4738982 | L42: =L38/L46 -> 2.6809411
B43: Diluted | C43: 0.12 | D43: -0.53 | E43: -0.31 | F43: 0.64 | G43: 1.09 | H43: =H38/H47 -> 1.6173928 | I43: =I38/I47 -> 1.9397547 | J43: =J38/J47 -> 2.2390374 | K43: =K38/K47 -> 2.4193671 | L43: =L38/L47 -> 2.6218462
B45: Shares used in calculation (000’s)
B46: Basic | C46: 74235 | D46: 83133 | E46: 84442 | F46: 85564 | G46: 86870 | H46: =G46 -> 86870 | I46: =H46 -> 86870 | J46: =I46 -> 86870 | K46: =J46 -> 86870 | L46: =K46 -> 86870
B47: Diluted | C47: 75679 | D47: 83133 | E47: 84442 | F47: 86957 | G47: 88828 | H47: =G47 -> 88828 | I47: =H47 -> 88828 | J47: =I47 -> 88828 | K47: =J47 -> 88828 | L47: =K47 -> 88828

Sheet Balance Sheet
B1: Balance Sheet - USD($) in thousands | C1: Actual | AA1: Expected
A2: x | C2: 2020A | D2: 2021 Q1 | E2: 2021 Q2 | F2: 2021 Q3 | G2: 2021 Q4 | H2: 2021A | I2: 2022 Q1 | J2: 2022 Q2 | K2: 2022 Q3 | L2: 2022 Q4 | M2: 2022A | N2: 2023 Q1 | O2: 2023 Q2 | P2: 2023 Q3 | Q2: 2023 Q4 | R2: 2023A | S2: 2024 Q1 | T2: 2024 Q2 | U2: 2024 Q3 | V2: 2024 Q4 | W2: 2024A | X2: 2025Q1 | Y2: 2025Q2 | Z2: 2025Q3 | AA2: 2025 | AB2: =AA2+1 -> 2026 | AC2: =AB2+1 -> 2027 | AD2: =AC2+1 -> 2028 | AE2: =AD2+1 -> 2029
B3: Assets
B4: Current assets
B5: Cash and cash equivalents | C5: 328803 | D5: 736773 | E5: 753754 | F5: 649129 | G5: 225414 | H5: =G5 -> 225414 | I5: 161247 | J5: =(176886*(1))*1 -> 176886 | K5: 210197 | L5: 254266 | M5: =L5 -> 254266 | N5: 225642 | O5: 290345 | P5: 334061 | Q5: 403979 | R5: =Q5 -> 403979 | S5: 251229 | T5: 326893 | U5: 322163 | V5: 295948 | W5: =V5 -> 295948 | X5: 287894 | Y5: 304461 | Z5: 309259 | AA5: ='Cash Flow Statement'!C35+W5 -> 751420.15 | AB5: ='Cash Flow Statement'!D35+AA5 -> 1208797.9 | AC5: ='Cash Flow Statement'!E35+AB5 -> 1679022.9 | AD5: ='Cash Flow Statement'!F35+AC5 -> 2127396.4 | AE5: ='Cash Flow Statement'!G35+AD5 -> 2598043.9
B6: Accounts receivable, net | C6: 72767 | D6: 74468 | E6: 74223 | F6: 84083 | G6: 87428 | H6: =G6 -> 87428 | I6: 86003 | J6: =(90426*(1))*1 -> 90426 | K6: 87716 | L6: 96835 | M6: =L6 -> 96835 | N6: 98414 | O6: 92581 | P6: 96181 | Q6: 104893 | R6: =Q6 -> 104893 | S6: 106218 | T6: 108454 | U6: 106712 | V6: 118006 | W6: =V6 -> 118006 | X6: 116256 | Y6: 111164 | Z6: 111243 | AA6: ='Balance Sheet Build'!H5*'annual IS'!H8 -> 142084.98 | AB6: ='Balance Sheet Build'!I5*'annual IS'!I8 -> 154163.41 | AC6: ='Balance Sheet Build'!J5*'annual IS'!J8 -> 166519.79 | AD6: ='Balance Sheet Build'!K5*'annual IS'!K8 -> 175582 | AE6: ='Balance Sheet Build'!L5*'annual IS'!L8 -> 185386.01
B7: Prepaid expenses and Other current assets | C7: 58607 | D7: 53870 | E7: 32637 | F7: 30919 | G7: 38495 | H7: =G7 -> 38495 | I7: 31673 | J7: =(41274*(1))*1 -> 41274 | K7: 34247 | L7: 31792 | M7: =L7 -> 31792 | N7: 34353 | O7: 39631 | P7: 44166 | Q7: 48564 | R7: =Q7 -> 48564 | S7: 47455 | T7: 60280 | U7: 66371 | V7: 63795 | W7: =V7 -> 63795 | X7: 68646 | Y7: 77207 | Z7: 78206 | AA7: ='Balance Sheet Build'!H7*'annual IS'!H8 -> 61900.476 | AB7: ='Balance Sheet Build'!I7*'annual IS'!I8 -> 67162.541 | AC7: ='Balance Sheet Build'!J7*'annual IS'!J8 -> 72545.7 | AD7: ='Balance Sheet Build'!K7*'annual IS'!K8 -> 76493.724 | AE7: ='Balance Sheet Build'!L7*'annual IS'!L8 -> 80764.922
B8: Total current assets | C8: =SUM(C5:C7) -> 460177 | D8: =SUM(D5:D7) -> 865111 | E8: =SUM(E5:E7) -> 860614 | F8: =SUM(F5:F7) -> 764131 | G8: =SUM(G5:G7) -> 351337 | H8: =G8 -> 351337 | I8: =SUM(I5:I7) -> 278923 | J8: =SUM(J5:J7) -> 308586 | K8: =SUM(K5:K7) -> 332160 | L8: =SUM(L5:L7) -> 382893 | M8: =L8 -> 382893 | N8: =SUM(N5:N7) -> 358409 | O8: =SUM(O5:O7) -> 422557 | P8: =SUM(P5:P7) -> 474408 | Q8: =SUM(Q5:Q7) -> 557436 | R8: =Q8 -> 557436 | S8: =SUM(S5:S7) -> 404902 | T8: =SUM(T5:T7) -> 495627 | U8: =SUM(U5:U7) -> 495246 | V8: =SUM(V5:V7) -> 477749 | W8: =V8 -> 477749 | X8: =SUM(X5:X7) -> 472796 | Y8: =SUM(Y5:Y7) -> 492832 | Z8: =SUM(Z5:Z7) -> 498708 | AA8: =SUM(AA5:AA7) -> 955405.61 | AB8: =SUM(AB5:AB7) -> 1430123.8 | AC8: =SUM(AC5:AC7) -> 1918088.3 | AD8: =SUM(AD5:AD7) -> 2379472.1 | AE8: =SUM(AE5:AE7) -> 2864194.8
B9: Property and equipment, net | C9: 29106 | D9: 27479 | E9: 27382 | F9: 24930 | G9: 23372 | H9: =G9 -> 23372 | I9: 21003 | J9: =(18028*(1))*1 -> 18028 | K9: 15620 | L9: 12862 | M9: =L9 -> 12862 | N9: 10532 | O9: 9145 | P9: 7660 | Q9: 6013 | R9: =Q9 -> 6013 | S9: 5083 | T9: 4592 | U9: 3890 | V9: 3239 | W9: =V9 -> 3239 | X9: 3173 | Y9: 3088 | Z9: 3390 | AA9: ='Balance Sheet Build'!H17 -> 1434.7951 | AB9: ='Balance Sheet Build'!I17 -> 567.13293 | AC9: ='Balance Sheet Build'!J17 -> 807.19999 | AD9: ='Balance Sheet Build'!K17 -> 2301.6739 | AE9: ='Balance Sheet Build'!L17 -> 5190.2502
B10: Operating lease right-of-use assets | C10: 89508 | D10: 86139 | E10: 83768 | F10: 81150 | G10: 63613 | H10: =G10 -> 63613 | I10: 62599 | J10: =(60588*(1))*1 -> 60588 | K10: 58536 | L10: 56461 | M10: =L10 -> 56461 | N10: 56726 | O10: 51976 | P10: 50329 | Q10: 48380 | R10: =Q10 -> 48380 | S10: 48108 | T10: 46484 | U10: 44845 | V10: 43185 | W10: =V10 -> 43185 | X10: 41446 | Y10: 39756 | Z10: 38045 | AA10: ='Balance Sheet Build'!H9*'annual IS'!H8 -> 44861.008 | AB10: ='Balance Sheet Build'!I9*'annual IS'!I8 -> 45041.522 | AC10: ='Balance Sheet Build'!J9*'annual IS'!J8 -> 44727.41 | AD10: ='Balance Sheet Build'!K9*'annual IS'!K8 -> 43023.723 | AE10: ='Balance Sheet Build'!L9*'annual IS'!L8 -> 41057.197
B11: Intangible assets, net | C11: 767003 | D11: 780794 | E11: 770329 | F11: 820946 | G11: 973137 | H11: =G11 -> 973137 | I11: 1007864 | J11: =(991945*(1))*1 -> 991945 | K11: 964531 | L11: 936359 | M11: =L11 -> 936359 | N11: 907703 | O11: 881937 | P11: 860514 | Q11: 835948 | R11: =Q11 -> 835948 | S11: 1071371 | T11: 1254210 | U11: 1228476 | V11: 1204658 | W11: =V11 -> 1204658 | X11: 1179430 | Y11: 1152456 | Z11: 1124768 | AA11: ='Balance Sheet Build'!H22 -> 1058149 | AB11: ='Balance Sheet Build'!I22 -> 928548.47 | AC11: ='Balance Sheet Build'!J22 -> 816904.47 | AD11: ='Balance Sheet Build'!K22 -> 718749.47 | AE11: ='Balance Sheet Build'!L22 -> 621619.47
B12: Goodwill | C12: 1327193 | D12: 1363568 | E12: 1363568 | F12: 1363549 | G12: 1645836 | H12: =G12 -> 1645836 | I12: 1645836 | J12: =(1645999*(1))*1 -> 1645999 | K12: 1645759 | L12: 1648145 | M12: =L12 -> 1648145 | N12: 1648145 | O12: 1648145 | P12: 1648145 | Q12: 1648145 | R12: =Q12 -> 1648145 | S12: 1648145 | T12: 1648145 | U12: 1648145 | V12: 1648145 | W12: =V12 -> 1648145 | X12: 1648145 | Y12: 1648145 | Z12: 1648145 | AA12: =W12 -> 1648145 | AB12: =X12 -> 1648145 | AC12: =Y12 -> 1648145 | AD12: =Z12 -> 1648145 | AE12: =AA12 -> 1648145
B13: Other assets | C13: 37420 | D13: 38778 | E13: 42973 | F13: 44908 | G13: 49807 | H13: =G13 -> 49807 | I13: 48842 | J13: =(48878*(1))*1 -> 48878 | K13: 48151 | L13: 52180 | M13: =L13 -> 52180 | N13: 53494 | O13: 52696 | P13: 52446 | Q13: 67868 | R13: =Q13 -> 67868 | S13: 68875 | T13: 65408 | U13: 67745 | V13: 71574 | W13: =V13 -> 71574 | X13: 71283 | Y13: 80401 | Z13: 85005 | AA13: ='Balance Sheet Build'!H11*'annual IS'!H8 -> 93755.431 | AB13: ='Balance Sheet Build'!I11*'annual IS'!I8 -> 103178.66 | AC13: ='Balance Sheet Build'!J11*'annual IS'!J8 -> 113018.25 | AD13: ='Balance Sheet Build'!K11*'annual IS'!K8 -> 120823.96 | AE13: ='Balance Sheet Build'!L11*'annual IS'!L8 -> 129317.98
B14: Total assets, non-current | C14: =SUM(C9:C13) -> 2250230 | D14: =SUM(D9:D13) -> 2296758 | E14: =SUM(E9:E13) -> 2288020 | F14: =SUM(F9:F13) -> 2335483 | G14: =SUM(G9:G13) -> 2755765 | H14: =SUM(H9:H13) -> 2755765 | I14: =SUM(I9:I13) -> 2786144 | J14: =SUM(J9:J13) -> 2765438 | ... AE14: =SUM(AE9:AE13) -> 2445329.9
B15: Total assets | C15: =SUM(C9:C13,C8) -> 2710407 | D15: =SUM(D9:D13,D8) -> 3161869 | E15: =SUM(E9:E13,E8) -> 3148634 | F15: =SUM(F9:F13,F8) -> 3099614 | G15: =SUM(G9:G13,G8) -> 3107102 | H15: =G15 -> 3107102 | I15: =SUM(I9:I13,I8) -> 3065067 | J15: =SUM(J9:J13,J8) -> 3074024 | K15: =SUM(K9:K13,K8) -> 3064757 | L15: =SUM(L9:L13,L8) -> 3088900 | M15: =L15 -> 3088900 | N15: =SUM(N9:N13,N8) -> 3035009 | O15: =SUM(O9:O13,O8) -> 3066456 | P15: =SUM(P9:P13,P8) -> 3093502 | Q15: =SUM(Q9:Q13,Q8) -> 3163790 | R15: =Q15 -> 3163790 | S15: =SUM(S9:S13,S8) -> 3246484 | T15: =SUM(T9:T13,T8) -> 3514466 | U15: =SUM(U9:U13,U8) -> 3488347 | V15: =SUM(V9:V13,V8) -> 3448550 | W15: =V15 -> 3448550 | X15: =W15 -> 3448550 | Y15: =X15 -> 3448550 | Z15: =Y15 -> 3448550 | AA15: =AA14+AA8 -> 3801750.8 | AB15: =AB14+AB8 -> 4155604.6 | AC15: =AC14+AC8 -> 4541690.7 | AD15: =AD14+AD8 -> 4912516 | AE15: =AE14+AE8 -> 5309524.7
B16: Liabilities and stockholders’ equity
B17: Current liabilities
B18: Accounts payable | C18: 1614 | D18: 9636 | E18: 4696 | F18: 5244 | G18: 2 | H18: 27541 | I18: 13661 | J18: =(15841*(1))*1 -> 15841 | K18: 15842 | L18: 13899 | M18: =L18 -> 13899 | N18: 13362 | O18: 12543 | P18: 13419 | Q18: 12041 | R18: =Q18 -> 12041 | S18: 18167 | T18: 10562 | U18: 10352 | V18: 14361 | W18: =V18 -> 14361 | X18: 13496 | Y18: 9600 | Z18: 19549 | AA18: ='Balance Sheet Build'!H32*'annual IS'!H15 -> 14956.662 | AB18: ='Balance Sheet Build'!I32*'annual IS'!I15 -> 15641.445 | AC18: ='Balance Sheet Build'!J32*'annual IS'!J15 -> 16369.475 | AD18: ='Balance Sheet Build'!K32*'annual IS'!K15 -> 17052.272 | AE18: ='Balance Sheet Build'!L32*'annual IS'!L15 -> 17788.783
B19: Accrued compensation | C19: 50670 | D19: 33045 | E19: 40154 | F19: 32695 | G19: -211.46912 | H19: 47136 | I19: 33405 | J19: =(41989*(1))*1 -> 41989 | K19: 35140 | L19: 45835 | M19: =L19 -> 45835 | N19: 20001 | O19: 31421 | P19: 31208 | Q19: 49608 | R19: =Q19 -> 49608 | S19: 23103 | T19: 37072 | U19: 47514 | V19: 69330 | W19: =V19 -> 69330 | X19: 24433 | Y19: 32482 | Z19: 43735 | AA19: ='Balance Sheet Build'!H34*'annual IS'!H25 -> 71628.365 | AB19: ='Balance Sheet Build'!I34*'annual IS'!I25 -> 73585.787 | AC19: ='Balance Sheet Build'!J34*'annual IS'!J25 -> 75615.782 | AD19: ='Balance Sheet Build'!K34*'annual IS'!K25 -> 75652.388 | AE19: ='Balance Sheet Build'!L34*'annual IS'!L25 -> 75570.38
B20: Accrued liabilities | C20: 75880 | D20: 73446 | E20: 49098 | F20: 49879 | G20: 30786.203 | H20: 57589 | I20: 47840 | J20: =(43287*(1))*1 -> 43287 | K20: 33367 | L20: 43668 | M20: =L20 -> 43668 | N20: 45647 | O20: 49281 | P20: 41840 | Q20: 46038 | R20: =Q20 -> 46038 | S20: 41192 | T20: 63379 | U20: 86725 | V20: 62631 | W20: =V20 -> 62631 | X20: 68444 | Y20: 64543 | Z20: 47413 | AA20: ='Balance Sheet Build'!H36*'annual IS'!H25 -> 68477.397 | AB20: ='Balance Sheet Build'!I36*'annual IS'!I25 -> 73772.157 | AC20: ='Balance Sheet Build'!J36*'annual IS'!J25 -> 79685.085 | AD20: ='Balance Sheet Build'!K36*'annual IS'!K25 -> 84021.643 | AE20: ='Balance Sheet Build'!L36*'annual IS'!L25 -> 88713.178
B21: Current portion of long-term debt | C21: 62500 | D21: 62500 | E21: 78125 | F21: 6563 | G21: 80272.687 | H21: 8750 | I21: 10938 | J21: =(13125*(1))*1 -> 13125 | K21: 15313 | L21: 17500 | M21: =L21 -> 17500 | N21: — | O21: — | P21: — | Q21: — | R21: 0 | S21: — | T21: — | U21: — | V21: — | W21: 0 | X21: — | Y21: — | Z21: — | AA21: 0 | AB21: 0 | AC21: 0 | AD21: 0 | AE21: 0
B22: Operating lease liabilities | C22: 14037 | D22: 13677 | E22: 13051 | F22: 12693 | G22: 92850.675 | H22: 12171 | I22: 11807 | J22: =(11275*(1))*1 -> 11275 | K22: 10713 | L22: 10159 | M22: =L22 -> 10159 | N22: 10646 | O22: 10026 | P22: 9769 | Q22: 9404 | R22: =Q22 -> 9404 | S22: 9755 | T22: 9895 | U22: 9948 | V22: 10001 | W22: =V22 -> 10001 | X22: 9969 | Y22: 9950 | Z22: 9931 | AA22: ='Balance Sheet Build'!H38*'annual IS'!H25 -> 15942.878 | AB22: ='Balance Sheet Build'!I38*'annual IS'!I25 -> 17175.602 | AC22: ='Balance Sheet Build'!J38*'annual IS'!J25 -> 18552.247 | AD22: ='Balance Sheet Build'!K38*'annual IS'!K25 -> 19561.883 | AE22: ='Balance Sheet Build'!L38*'annual IS'!L25 -> 20654.164
B23: Total current liabilities | C23: =SUM(C18:C22) -> 204701 | D23: =SUM(D18:D22) -> 192304 | E23: =SUM(E18:E22) -> 185124 | F23: =SUM(F18:F22) -> 107074 | G23: 153187 | H23: =G23 -> 153187 | I23: =SUM(I18:I22) -> 117651 | J23: =SUM(J18:J22) -> 125517 | K23: =SUM(K18:K22) -> 110375 | L23: =SUM(L18:L22) -> 131061 | M23: =L23 -> 131061 | N23: =SUM(N18:N22) -> 89656 | O23: =SUM(O18:O22) -> 103271 | P23: =SUM(P18:P22) -> 96236 | Q23: =SUM(Q18:Q22) -> 117091 | R23: =Q23 -> 117091 | S23: =SUM(S18:S22) -> 92217 | T23: =SUM(T18:T22) -> 120908 | U23: =SUM(U18:U22) -> 154539 | V23: =SUM(V18:V22) -> 156323 | W23: =V23 -> 156323 | X23: =SUM(X18:X22) -> 116342 | Y23: =SUM(Y18:Y22) -> 116575 | Z23: =SUM(Z18:Z22) -> 120628 | AA23: =SUM(AA18:AA22) -> 171005.3 | AB23: =SUM(AB18:AB22) -> 180174.99 | AC23: =SUM(AC18:AC22) -> 190222.59 | AD23: =SUM(AD18:AD22) -> 196288.19 | AE23: =SUM(AE18:AE22) -> 202726.51
B24: Long-term liabilities
B25: Long-term debt, net | C25: 924217 | D25: 909820 | E25: 895449 | F25: 923501 | G25: 922077 | H25: =G25 -> 922077 | I25: 918514 | J25: =(914966*(1))*1 -> 914966 | K25: 911406 | L25: 907838 | M25: =L25 -> 907838 | N25: 872902 | O25: 873581 | P25: 874270 | Q25: 874972 | R25: =Q25 -> 874972 | S25: 925675 | T25: 1101400 | U25: 1081039 | V25: 1056301 | W25: =V25 -> 1056301 | X25: 1056566 | Y25: 1006834 | Z25: 982105 | AA25: ='Balance Sheet Build'!H41*'annual IS'!H8 -> 1152410.5 | AB25: ='Balance Sheet Build'!I41*'annual IS'!I8 -> 1221310.7 | AC25: ='Balance Sheet Build'!J41*'annual IS'!J8 -> 1287806.3 | AD25: ='Balance Sheet Build'!K41*'annual IS'!K8 -> 1324787.8 | AE25: ='Balance Sheet Build'!L41*'annual IS'!L8 -> 1363809.5
B26: Operating lease liabilities, non-current | C26: 74224 | D26: 71916 | E26: 69998 | F26: 67836 | G26: 65232 | H26: =G26 -> 65232 | I26: 64344 | J26: =(62626*(1))*1 -> 62626 | K26: 60819 | L26: 58988 | M26: =L26 -> 58988 | N26: 58625 | O26: 52371 | P26: 50580 | Q26: 48766 | R26: =Q26 -> 48766 | S26: 48253 | T26: 46158 | U26: 44202 | V26: 42219 | W26: =V26 -> 42219 | X26: 40223 | Y26: 38240 | Z26: 36228 | AA26: ='Balance Sheet Build'!H43*'Expense Build'!AA15 -> 45642.756 | AB26: ='Balance Sheet Build'!I43*'Expense Build'!AB15 -> 45590.938 | AC26: ='Balance Sheet Build'!J43*'Expense Build'!AC15 -> 45377.112 | AD26: ='Balance Sheet Build'!K43*'Expense Build'!AD15 -> 43768.093 | AE26: ='Balance Sheet Build'!L43*'Expense Build'!AE15 -> 41905.754
B27: Other long-term liabilities | C27: 8808 | D27: 14811 | E27: 20091 | F27: 18953 | G27: 14185 | H27: =G27 -> 14185 | I27: 13919 | J27: 13731 | K27: 9758 | L27: 12708 | M27: =L27 -> 12708 | N27: 13307 | O27: 13092 | P27: 17711 | Q27: 19270 | R27: =Q27 -> 19270 | S27: 19273 | T27: 25497 | U27: 25275 | V27: 22962 | W27: =V27 -> 22962 | X27: 22178 | Y27: 21993 | Z27: 23501 | AA27: ='Balance Sheet Build'!H45*'annual IS'!H8 -> 22479.822 | AB27: ='Balance Sheet Build'!I45*'annual IS'!I8 -> 24390.798 | AC27: ='Balance Sheet Build'!J45*'annual IS'!J8 -> 26345.75 | AD27: ='Balance Sheet Build'!K45*'annual IS'!K8 -> 27779.517 | AE27: ='Balance Sheet Build'!L45*'annual IS'!L8 -> 29330.648
B28: Deferred tax liability | C28: 119729 | D28: 124748 | E28: 115306 | F28: 110400 | G28: 99846 | H28: =G28 -> 99846 | I28: 95376 | J28: =(92288*(1))*1 -> 92288 | K28: 89281 | L28: 82665 | M28: =L28 -> 82665 | N28: 81927 | O28: 74527 | P28: 66737 | Q28: 68670 | R28: =Q28 -> 68670 | S28: 63282 | T28: 63466 | U28: 58605 | V28: 55834 | W28: =V28 -> 55834 | X28: 57158 | Y28: 86615 | Z28: 101573 | AA28: ='Balance Sheet Build'!H47*'annual IS'!H8 -> 55633.264 | AB28: ='Balance Sheet Build'!I47*'annual IS'!I8 -> 53096.461 | AC28: ='Balance Sheet Build'!J47*'annual IS'!J8 -> 49503.717 | AD28: ='Balance Sheet Build'!K47*'annual IS'!K8 -> 43922.154 | AE28: ='Balance Sheet Build'!L47*'annual IS'!L8 -> 37636.945
B29: Total long-term liabilities | C29: =SUM(C25:C28) -> 1126978 | D29: =SUM(D25:D28) -> 1121295 | E29: =SUM(E25:E28) -> 1100844 | F29: =SUM(F25:F28) -> 1120690 | G29: =SUM(G25:G28) -> 1101340 | H29: =SUM(H25:H28) -> 1101340 | I29: =SUM(I25:I28) -> 1092153 | J29: =SUM(J25:J28) -> 1083611 | ... AE29: =SUM(AE25:AE28) -> 1472682.8
B30: Total liabilities | C30: =SUM(C29,C23) -> 1331679 | D30: =SUM(D29,D23) -> 1313599 | E30: =SUM(E29,E23) -> 1285968 | F30: =SUM(F29,F23) -> 1227764 | G30: =SUM(G29,G23) -> 1254527 | H30: =G30 -> 1254527 | I30: =SUM(I29,I23) -> 1209804 | J30: =SUM(J29,J23) -> 1209128 | K30: =SUM(K29,K23) -> 1181639 | L30: =SUM(L29,L23) -> 1193260 | M30: =L30 -> 1193260 | N30: =SUM(N29,N23) -> 1116417 | O30: =SUM(O29,O23) -> 1116842 | P30: =SUM(P29,P23) -> 1105534 | Q30: =SUM(Q29,Q23) -> 1128769 | R30: =Q30 -> 1128769 | S30: =SUM(S29,S23) -> 1148700 | T30: =SUM(T29,T23) -> 1357429 | U30: =SUM(U29,U23) -> 1363660 | V30: =SUM(V29,V23) -> 1333639 | W30: =V30 -> 1333639 | X30: =SUM(X29,X23) -> 1292467 | Y30: =SUM(Y29,Y23) -> 1270257 | Z30: =SUM(Z29,Z23) -> 1264035 | AA30: =AA29+AA23 -> 1447171.6 | AB30: =AB29+AB23 -> 1524563.9 | AC30: =AC29+AC23 -> 1599255.5 | AD30: =AD29+AD23 -> 1636545.8 | AE30: =AE29+AE23 -> 1675409.3
B31: Stockholders’ equity
B32: Preferred stock, | H32: =G32 -> 0 | M32: =L32 -> 0 | R32: =Q32 -> 0 | W32: =V32 -> 0 | AA32: 0 | AB32: 0 | AC32: 0 | AD32: 0 | AE32: 0
B33: Common stock, | C33: 8 | D33: 8 | E33: 8 | F33: 8 | G33: 8 | H33: =G33 -> 8 | I33: 8 | J33: =(8*(1))*1 -> 8 | K33: 8 | L33: 8 | M33: =L33 -> 8 | N33: 9 | O33: 9 | P33: 9 | Q33: 9 | R33: =Q33 -> 9 | S33: 9 | T33: 9 | U33: 9 | V33: 9 | W33: =V33 -> 9 | X33: 9 | Y33: 9 | Z33: 9 | AA33: =W33 -> 9 | AB33: =X33 -> 9 | AC33: =Y33 -> 9 | AD33: =Z33 -> 9 | AE33: =AA33 -> 9
B34: Additional paid-in capital | C34: 1158372 | D34: 1630529 | E34: 1648743 | F34: 1662965 | G34: 1676508 | H34: =G34 -> 1676508 | I34: 1692835 | J34: =(1713122*(1))*1 -> 1713122 | K34: 1732985 | L34: 1745716 | M34: =L34 -> 1745716 | N34: 1764573 | O34: 1785014 | P34: 1808695 | Q34: 1829384 | R34: =Q34 -> 1829384 | S34: 1863334 | T34: 1886765 | U34: 1893088 | V34: 1905628 | W34: =V34 -> 1905628 | X34: 1905444 | Y34: 1919312 | Z34: 1917244 | AA34: ='Balance Sheet Build'!H54 -> 2001626.5 | AB34: ='Balance Sheet Build'!I54 -> 2105783.4 | AC34: ='Balance Sheet Build'!J54 -> 2218288.7 | AD34: ='Balance Sheet Build'!K54 -> 2336916.7 | AE34: ='Balance Sheet Build'!L54 -> 2462168.5
B35: Accumulated Other Comprehensive Earnings | H35: =G35 -> 0 | M35: =L35 -> 0 | R35: =Q35 -> 0 | W35: =V35 -> 0 | Y35: 203 | Z35: 8837 | AA35: 0 | AB35: =AA35 -> 0 | AC35: =AB35 -> 0 | AD35: =AC35 -> 0 | AE35: =AD35 -> 0
B36: Accumulated earnings | C36: 220348 | D36: 217733 | E36: 213915 | F36: 208877 | G36: 176059 | H36: =G36 -> 176059 | I36: 162420 | J36: =(151766*(1))*1 -> 151766 | K36: 150125 | L36: 149916 | M36: =L36 -> 149916 | N36: 154010 | O36: 164591 | P36: 179264 | Q36: 205628 | R36: =Q36 -> 205628 | S36: 234441 | T36: 270263 | U36: 231590 | V36: 209274 | W36: =V36 -> 209274 | X36: 218353 | Y36: 226897 | Z36: 207936 | AA36: ='Balance Sheet Build'!H61 -> 352943.77 | AB36: ='Balance Sheet Build'!I61 -> 525248.3 | AC36: ='Balance Sheet Build'!J61 -> 724137.51 | AD36: ='Balance Sheet Build'!K61 -> 939045.05 | AE36: ='Balance Sheet Build'!L61 -> 1171938.4
B37: Total stockholders’ equity | C37: =SUM(C33:C36) -> 1378728 | D37: =SUM(D33:D36) -> 1848270 | E37: =SUM(E33:E36) -> 1862666 | F37: =SUM(F33:F36) -> 1871850 | G37: =SUM(G33:G36) -> 1852575 | H37: =G37 -> 1852575 | I37: =SUM(I33:I36) -> 1855263 | J37: =SUM(J33:J36) -> 1864896 | K37: =SUM(K33:K36) -> 1883118 | L37: =SUM(L33:L36) -> 1895640 | M37: =L37 -> 1895640 | N37: =SUM(N33:N36) -> 1918592 | O37: =SUM(O33:O36) -> 1949614 | P37: =SUM(P33:P36) -> 1987968 | Q37: =SUM(Q33:Q36) -> 2035021 | R37: =Q37 -> 2035021 | S37: =SUM(S33:S36) -> 2097784 | T37: =SUM(T33:T36) -> 2157037 | U37: =SUM(U33:U36) -> 2124687 | V37: =SUM(V33:V36) -> 2114911 | W37: =V37 -> 2114911 | X37: =SUM(X33:X36) -> 2123806 | Y37: =SUM(Y33:Y36) -> 2146421 | Z37: =SUM(Z33:Z36) -> 2134026 | AA37: =SUM(AA32:AA36) -> 2354579.2 | AB37: =SUM(AB32:AB36) -> 2631040.7 | AC37: =SUM(AC32:AC36) -> 2942435.2 | AD37: =SUM(AD32:AD36) -> 3275970.7 | AE37: =SUM(AE32:AE36) -> 3634115.9
B38: Total liabilities and stockholders’ equity | C38: =SUM(C37,C30) -> 2710407 | D38: =SUM(D37,D30) -> 3161869 | E38: =SUM(E37,E30) -> 3148634 | F38: =SUM(F37,F30) -> 3099614 | G38: =SUM(G37,G30) -> 3107102 | H38: =G38 -> 3107102 | I38: =SUM(I37,I30) -> 3065067 | J38: =SUM(J37,J30) -> 3074024 | K38: =SUM(K37,K30) -> 3064757 | L38: =SUM(L37,L30) -> 3088900 | M38: =L38 -> 3088900 | N38: =SUM(N37,N30) -> 3035009 | O38: =SUM(O37,O30) -> 3066456 | P38: =SUM(P37,P30) -> 3093502 | Q38: =SUM(Q37,Q30) -> 3163790 | R38: =Q38 -> 3163790 | S38: =SUM(S37,S30) -> 3246484 | T38: =SUM(T37,T30) -> 3514466 | U38: =SUM(U37,U30) -> 3488347 | V38: =SUM(V37,V30) -> 3448550 | W38: =V38 -> 3448550 | X38: =SUM(X37,X30) -> 3416273 | Y38: =SUM(Y37,Y30) -> 3416678 | Z38: =SUM(Z37,Z30) -> 3398061 | AA38: =AA37+AA30 -> 3801750.8 | AB38: =AB37+AB30 -> 4155604.6 | AC38: =AC37+AC30 -> 4541690.7 | AD38: =AD37+AD30 -> 4912516.5 | AE38: =AE37+AE30 -> 5309525.2
B40: CHECK | C40: =C38-C15 -> 0 | D40: =D38-D15 -> 0 | E40: =E38-E15 -> 0 | F40: =F38-F15 -> 0 | G40: =G38-G15 -> 0 | H40: =H38-H15 -> 0 | I40: =I38-I15 -> 0 | J40: =J38-J15 -> 0 | ... AE40: =AE38-AE15 -> 0.47429685

Sheet Expense Build
B1: Expense Build- USD($) and shares in thousands | C1: Actual | AA1: Expected
C2: 2020A | D2: 2021 Q1 | E2: 2021 Q2 | F2: 2021 Q3 | G2: 2021 Q4 | H2: 2021A | I2: 2022 Q1 | J2: 2022 Q2 | K2: 2022 Q3 | L2: 2022 Q4 | M2: 2022A | N2: 2023 Q1 | O2: 2023 Q2 | P2: 2023 Q3 | Q2: 2023 Q4 | R2: 2023A | S2: 2024 Q1 | T2: 2024 Q2 | U2: 2024 Q3 | V2: 2024 Q4 | W2: 2024A | X2: 2024A | Y2: 2024A | Z2: 2024A | AA2: 2025 | AB2: =AA2+1 -> 2026 | AC2: =AB2+1 -> 2027 | AD2: =AC2+1 -> 2028 | AE2: =AD2+1 -> 2029
B4: Operating Expenses:
B5: Service Costs | C5: ='quarterly IS'!C11 -> 280214 | D5: ='quarterly IS'!D11 -> 70632 | E5: ='quarterly IS'!E11 -> 67334 | F5: ='quarterly IS'!F11 -> 66217 | G5: ='quarterly IS'!G11 -> 86119 | H5: ='quarterly IS'!H11 -> 290302 | I5: ='quarterly IS'!I11 -> 80874 | J5: ='quarterly IS'!J11 -> 74914 | ... Z5: ='quarterly IS'!Z11 -> 76889 | AA5: =AA27*'annual IS'!H5 -> 353773.74 | AB5: =AB27*'annual IS'!I5 -> 369088.02 | AC5: =AC27*'annual IS'!J5 -> 386377.51 | AD5: =AD27*'annual IS'!K5 -> 404985.21 | AE5: =AE27*'annual IS'!L5 -> 425264.57
B6: Custodial Costs | C6: ='quarterly IS'!C12 -> 19574 | D6: ='quarterly IS'!D12 -> 5009 | E6: ='quarterly IS'!E12 -> 4824 | F6: ='quarterly IS'!F12 -> 5734 | G6: ='quarterly IS'!G12 -> 6300 | H6: ='quarterly IS'!H12 -> 21867 | I6: ='quarterly IS'!I12 -> 6641 | J6: ='quarterly IS'!J12 -> 7090 | ... Z6: ='quarterly IS'!Z12 -> 10879 | AA6: =AA28*'annual IS'!H6 -> 48163.24 | AB6: =AB28*'annual IS'!I6 -> 50872.582 | AC6: =AC28*'annual IS'!J6 -> 52628.822 | AD6: =AD28*'annual IS'!K6 -> 51576.479 | AE6: =AE28*'annual IS'!L6 -> 50189.213
B7: Interchange Costs | C7: ='quarterly IS'!C13 -> 18448 | D7: ='quarterly IS'!D13 -> 5445 | E7: ='quarterly IS'!E13 -> 4974 | F7: ='quarterly IS'!F13 -> 4683 | G7: ='quarterly IS'!G13 -> 5579 | H7: ='quarterly IS'!H13 -> 20681 | I7: ='quarterly IS'!I13 -> 6991 | J7: ='quarterly IS'!J13 -> 6326 | ... Z7: ='quarterly IS'!Z13 -> 6333 | AA7: =AA29*'annual IS'!H7 -> 31520.695 | AB7: =AB29*'annual IS'!I7 -> 33342.741 | AC7: =AC29*'annual IS'!J7 -> 35395.973 | AD7: =AD29*'annual IS'!K7 -> 37628.696 | AE7: =AE29*'annual IS'!L7 -> 40081.359
B8: Total COGS | C8: =SUM(C5:C7) -> 318236 | D8: =SUM(D5:D7) -> 81086 | E8: =SUM(E5:E7) -> 77132 | F8: =SUM(F5:F7) -> 76634 | G8: =SUM(G5:G7) -> 97998 | H8: =SUM(H5:H7) -> 332850 | I8: =SUM(I5:I7) -> 94506 | J8: =SUM(J5:J7) -> 88330 | ... AE8: =SUM(AE5:AE7) -> 515535.14
B10: Sales and marketing | C10: ='quarterly IS'!C19 -> 49964 | D10: ='quarterly IS'!D19 -> 14086 | E10: ='quarterly IS'!E19 -> 15476 | F10: ='quarterly IS'!F19 -> 12726 | G10: ='quarterly IS'!G19 -> 16317 | H10: ='quarterly IS'!H19 -> 58605 | I10: ='quarterly IS'!I19 -> 16560 | J10: ='quarterly IS'!J19 -> 15843 | ... Z10: ='quarterly IS'!Z19 -> 24411 | AA10: =AA32*'annual IS'!$H$8 -> 101899.84 | AB10: =AB32*'annual IS'!$I$8 -> 110562.19 | AC10: =AC32*'annual IS'!$J$8 -> 119423.88 | AD10: =AD32*'annual IS'!$K$8 -> 125923.07 | AE10: =AE32*'annual IS'!$L$8 -> 132954.27
B11: Technology and development | C11: ='quarterly IS'!C20 -> 124809 | D11: ='quarterly IS'!D20 -> 35469 | E11: ='quarterly IS'!E20 -> 37898 | F11: ='quarterly IS'!F20 -> 38070 | G11: ='quarterly IS'!G20 -> 45927 | H11: ='quarterly IS'!H20 -> 157364 | I11: ='quarterly IS'!I20 -> 45183 | J11: ='quarterly IS'!J20 -> 46580 | ... Z11: ='quarterly IS'!Z20 -> 65916 | AA11: =AA33*'annual IS'!$H$8 -> 273517.1 | AB11: =AB33*'annual IS'!$I$8 -> 296768.37 | AC11: =AC33*'annual IS'!$J$8 -> 320554.72 | AD11: =AD33*'annual IS'!$K$8 -> 337999.69 | AE11: =AE33*'annual IS'!$L$8 -> 356872.66
B12: General and administrative | C12: ='quarterly IS'!C21 -> 84493 | D12: ='quarterly IS'!D21 -> 20687 | E12: ='quarterly IS'!E21 -> 22812 | F12: ='quarterly IS'!F21 -> 20004 | G12: ='quarterly IS'!G21 -> 20876 | H12: ='quarterly IS'!H21 -> 84379 | I12: ='quarterly IS'!I21 -> 23727 | J12: ='quarterly IS'!J21 -> 25937 | ... Z12: ='quarterly IS'!Z21 -> 30880 | AA12: =AA34*'annual IS'!$H$8 -> 148336.32 | AB12: =AB34*'annual IS'!$I$8 -> 160946.17 | AC12: =AC34*'annual IS'!$J$8 -> 173846.19 | AD12: =AD34*'annual IS'!$K$8 -> 183307.11 | AE12: =AE34*'annual IS'!$L$8 -> 193542.47
B13: Amortization of acquired intangible assets | C13: ='quarterly IS'!C22 -> 76064 | D13: ='quarterly IS'!D22 -> 19814 | E13: ='quarterly IS'!E22 -> 20289 | F13: ='quarterly IS'!F22 -> 19642 | G13: ='quarterly IS'!G22 -> 23046 | H13: ='quarterly IS'!H22 -> 82791 | I13: ='quarterly IS'!I22 -> 23698 | J13: ='quarterly IS'!J22 -> 24181 | ... Z13: ='quarterly IS'!Z22 -> 27002 | AA13: =AA35*'annual IS'!$H$8 -> 136329.18 | AB13: =AB35*'annual IS'!$I$8 -> 147918.31 | AC13: =AC35*'annual IS'!$J$8 -> 159774.14 | AD13: =AD35*'annual IS'!$K$8 -> 168469.24 | AE13: =AE35*'annual IS'!$L$8 -> 177876.1
B14: Merger Integration | C14: ='quarterly IS'!C23 -> 45990 | D14: ='quarterly IS'!D23 -> 8807 | E14: ='quarterly IS'!E23 -> 16371 | F14: ='quarterly IS'!F23 -> 13244 | G14: ='quarterly IS'!G23 -> 26383 | H14: ='quarterly IS'!H23 -> 64805 | I14: ='quarterly IS'!I23 -> 9294 | J14: ='quarterly IS'!J23 -> 7683 | ... Z14: ='quarterly IS'!Z23 -> 1159 | AA14: 4710 | AB14: 0 | AC14: 0 | AD14: 0 | AE14: 0
B15: Total Operating Expenses: | C15: =SUM(C10:C14) -> 381320 | D15: =SUM(D10:D14) -> 98863 | E15: =SUM(E10:E14) -> 112846 | F15: =SUM(F10:F14) -> 103686 | G15: =SUM(G10:G14) -> 132549 | H15: =SUM(H10:H14) -> 447944 | I15: =SUM(I10:I14) -> 118462 | J15: =SUM(J10:J14) -> 120224 | ... AE15: =SUM(AE10:AE14) -> 861245.5
B17: Non-operating Expenses:
B18: Interest expense (negative is expense) | C18: ='quarterly IS'!C30 -> -34881 | D18: ='quarterly IS'!D30 -> -6689 | E18: ='quarterly IS'!E30 -> -7254 | F18: ='quarterly IS'!F30 -> -11881 | G18: ='quarterly IS'!G30 -> -10748 | H18: ='quarterly IS'!H30 -> -36572 | I18: ='quarterly IS'!I30 -> -10461 | J18: ='quarterly IS'!J30 -> -11493 | ... Z18: ='quarterly IS'!Z30 -> -14049 | AA18: =AA38*'[1]Balance Sheet'!AA25 -> -57102.601 | AB18: =AB38*'[1]Balance Sheet'!AB25 -> -60516.648 | AC18: =AC38*'[1]Balance Sheet'!AC25 -> -63811.542 | AD18: =AD38*'[1]Balance Sheet'!AD25 -> -65643.997 | AE18: =AE38*'[1]Balance Sheet'!AE25 -> -67577.543
B19: Other income, net (negative is expense) | C19: ='quarterly IS'!C31 -> 5007 | D19: ='quarterly IS'!D31 -> -3630 | E19: ='quarterly IS'!E31 -> 344 | F19: ='quarterly IS'!F31 -> 3122 | G19: ='quarterly IS'!G31 -> -5767 | H19: ='quarterly IS'!H31 -> -5931 | I19: ='quarterly IS'!I31 -> -301 | J19: ='quarterly IS'!J31 -> 32 | ... Z19: ='quarterly IS'!Z31 -> 2886 | AA19: ='[1]annual IS'!H31 -> 5627.4461 | AB19: ='[1]annual IS'!I31 -> 6105.8267 | AC19: ='[1]annual IS'!J31 -> 6595.2161 | AD19: ='[1]annual IS'!K31 -> 6954.1357 | AE19: ='[1]annual IS'!L31 -> 7342.4353
B20: Provision for income taxes (benefit) | C20: ='quarterly IS'!C34 -> -4694 | D20: ='quarterly IS'!D34 -> -3451 | E20: ='quarterly IS'!E34 -> -3967 | F20: ='quarterly IS'!F34 -> -4087 | G20: ='quarterly IS'!G34 -> -10947 | H20: ='quarterly IS'!H34 -> -22452 | I20: ='quarterly IS'!I34 -> -4412 | J20: ='quarterly IS'!J34 -> -3219 | ... Z20: ='quarterly IS'!Z34 -> 15840 | AA20: ='[1]annual IS'!H34 -> 45968.257 | AB20: ='[1]annual IS'!I34 -> 57006.796 | AC20: ='[1]annual IS'!J34 -> 65591.125 | AD20: ='[1]annual IS'!K34 -> 71635.847 | AE20: ='[1]annual IS'!L34 -> 77631.118
B21: Total Non-operating Expenses: | C21: =-C18+-C19+C20 -> 25180 | D21: =-D18+-D19+D20 -> 6868 | E21: =-E18+-E19+E20 -> 2943 | F21: =-F18+-F19+F20 -> 4672 | G21: =-G18+-G19+G20 -> 5568 | H21: =-H18+-H19+H20 -> 20051 | I21: =-I18+-I19+I20 -> 6350 | J21: =-J18+-J19+J20 -> 8242 | ... AE21: =-AE18+-AE19+AE20 -> 137866.23
B23: Total Expenses: | C23: =SUM(C21,C15,C8) -> 724736 | D23: =SUM(D21,D15,D8) -> 186817 | E23: =SUM(E21,E15,E8) -> 192921 | F23: =SUM(F21,F15,F8) -> 184992 | G23: =SUM(G21,G15,G8) -> 236115 | H23: =SUM(H21,H15,H8) -> 800845 | I23: =SUM(I21,I15,I8) -> 219318 | J23: =SUM(J21,J15,J8) -> 216796 | ... AE23: =SUM(AE21,AE15,AE8) -> 1514646.9
B25: Expense Build Drivers:
B26: COGS Drivers:
B27: Service Costs - % of service revenue | C27: =C5/'annual IS'!C5 -> 0.65019978 | D27: =D5/'annual IS'!D5 -> 0.16544939 | E27: =E5/'annual IS'!E5 -> 0.14896046 | F27: =F5/'annual IS'!F5 -> 0.14531151 | G27: =G5/'annual IS'!G5 -> 0.18004587 | H27: =H5/'annual IS'!D5 -> 0.6800075 | I27: =I5/'annual IS'!I5 -> 0.15995648 | J27: =J5/'annual IS'!J5 -> 0.14347719 | K27: =K5/'annual IS'!K5 -> 0.14165888 | L27: =L5/'annual IS'!L5 -> 0.15411253 | M27: =M5/'annual IS'!E5 -> 0.70464088 | N27: =N5/'annual IS'!N5 -> #DIV/0! | O27: =O5/'annual IS'!O5 -> #DIV/0! | P27: =P5/'annual IS'!P5 -> #DIV/0! | Q27: =Q5/'annual IS'!Q5 -> #DIV/0! | R27: =R5/'annual IS'!F5 -> 0.69643178 | S27: =S5/'annual IS'!S5 -> #DIV/0! | T27: =T5/'annual IS'!T5 -> #DIV/0! | U27: =U5/'annual IS'!U5 -> #DIV/0! | V27: =V5/'annual IS'!V5 -> #DIV/0! | W27: =W5/'annual IS'!G5 -> 0.73505228 | X27: =X5/'quarterly IS'!X4 -> 0.73469132 | Y27: =Y5/'quarterly IS'!Y4 -> 0.63760149 | Z27: =Z5/'quarterly IS'!Z4 -> 0.6392182 | AA27: 0.72 | AB27: =AA27+$AF$27 -> 0.73 | AC27: =AB27+$AF$27 -> 0.74 | AD27: =AC27+$AF$27 -> 0.75 | AE27: =AD27+$AF$27 -> 0.76 | AF27: 0.01 | AG27: (+)
B28: Custodial Costs - % of custodial revenue | C28: =C6/'annual IS'!C6 -> 0.10251764 | D28: =D6/'quarterly IS'!D5 -> 0.10662438 | E28: =E6/'quarterly IS'!E5 -> 0.098901099 | F28: =F6/'quarterly IS'!F5 -> 0.11700608 | G28: =G6/'quarterly IS'!G5 -> 0.10851405 | H28: =H6/'annual IS'!D6 -> 0.10781641 | I28: =I6/'annual IS'!I6 -> 0.0088432831 | J28: =J6/'annual IS'!J6 -> 0.0084525397 | K28: =K6/'annual IS'!K6 -> 0.0076264354 | L28: =L6/'annual IS'!L6 -> 0.0058407984 | M28: =M6/'annual IS'!E6 -> 0.099895898 | N28: =N6/'annual IS'!N6 -> #DIV/0! | O28: =O6/'annual IS'!O6 -> #DIV/0! | P28: =P6/'annual IS'!P6 -> #DIV/0! | Q28: =Q6/'annual IS'!Q6 -> #DIV/0! | R28: =R6/'annual IS'!F6 -> 0.084072696 | S28: =S6/'annual IS'!S6 -> #DIV/0! | T28: =T6/'annual IS'!T6 -> #DIV/0! | U28: =U6/'annual IS'!U6 -> #DIV/0! | V28: =V6/'annual IS'!V6 -> #DIV/0! | W28: =W6/'annual IS'!G6 -> 0.072742907 | X28: =X6/'quarterly IS'!X5 -> 0.068690678 | Y28: =Y6/'quarterly IS'!Y5 -> 0.069660237 | Z28: =Z6/'quarterly IS'!Z5 -> 0.068392564 | AA28: =W28 -> 0.072742907 | AB28: =AA28-$AF$28 -> 0.067742907 | AC28: =AB28-$AF$28 -> 0.062742907 | AD28: =AC28-$AF$28 -> 0.057742907 | AE28: =AD28-$AF$28 -> 0.052742907 | AF28: 0.005 | AG28: (-)
B29: Interchange Cost - % of interchange revenue | C29: =C7/'annual IS'!C7 -> 0.16519956 | D29: =D7/'quarterly IS'!D6 -> 0.15696166 | E29: =E7/'quarterly IS'!E6 -> 0.15970461 | F29: =F7/'quarterly IS'!F6 -> 0.16597554 | G29: =G7/'quarterly IS'!G6 -> 0.17020043 | H29: =H7/'annual IS'!D7 -> 0.16306208 | I29: =I7/'annual IS'!I7 -> 0.035549555 | J29: =J7/'annual IS'!J7 -> 0.030302014 | K29: =K7/'annual IS'!K7 -> 0.026688166 | L29: =L7/'annual IS'!L7 -> 0.025194655 | M29: =M7/'annual IS'!E7 -> 0.16973861 | N29: =N7/'annual IS'!N7 -> #DIV/0! | O29: =O7/'annual IS'!O7 -> #DIV/0! | P29: =P7/'annual IS'!P7 -> #DIV/0! | Q29: =Q7/'annual IS'!Q7 -> #DIV/0! | R29: =R7/'annual IS'!F7 -> 0.17222176 | S29: =S7/'annual IS'!S7 -> #DIV/0! | T29: =T7/'annual IS'!T7 -> #DIV/0! | U29: =U7/'annual IS'!U7 -> #DIV/0! | V29: =V7/'annual IS'!V7 -> #DIV/0! | W29: =W7/'annual IS'!G7 -> 0.17752481 | X29: =X7/'quarterly IS'!X6 -> 0.14249611 | Y29: =Y7/'quarterly IS'!Y6 -> 0.14447032 | Z29: =Z7/'quarterly IS'!Z6 -> 0.14792927 | AA29: =AVERAGE(C29,H29,M29,R29,W29) -> 0.16954936 | AB29: =AA29 -> 0.16954936 | AC29: =AB29 -> 0.16954936 | AD29: =AC29 -> 0.16954936 | AE29: =AD29 -> 0.16954936
D30: =SUM(D27:D29) -> 0.42903543 | E30: =SUM(E27:E29) -> 0.40756616 | F30: =SUM(F27:F29) -> 0.42829313 | G30: =SUM(G27:G29) -> 0.45876035
B31: Operating Expense Drivers:
B32: Sales & Marketing - % of Revenue | C32: =C10/'annual IS'!C8 -> 0.068110746 | D32: =D10/'annual IS'!D8 -> 0.018618582 | E32: =E10/'annual IS'!E8 -> 0.017958846 | F32: =F10/'annual IS'!F8 -> 0.012731258 | G32: =G10/'annual IS'!G8 -> 0.013600061 | H32: =H10/'annual IS'!$D$8 -> 0.077462871 | I32: =I10/'annual IS'!I8 -> 0.01139538 | J32: =J10/'annual IS'!J8 -> 0.010093025 | K32: =K10/'annual IS'!K8 -> 0.010419167 | L32: =L10/'annual IS'!L8 -> 0.010987444 | M32: =M10/'annual IS'!$E$8 -> 0.079894586 | N32: =N10/'annual IS'!N8 -> #DIV/0! | O32: =O10/'annual IS'!O8 -> #DIV/0! | P32: =P10/'annual IS'!P8 -> #DIV/0! | Q32: =Q10/'annual IS'!Q8 -> #DIV/0! | R32: =R10/'annual IS'!$F$8 -> 0.079305753 | S32: =S10/'annual IS'!S8 -> #DIV/0! | T32: =T10/'annual IS'!T8 -> #DIV/0! | U32: =U10/'annual IS'!U8 -> #DIV/0! | V32: =V10/'annual IS'!V8 -> #DIV/0! | W32: =W10/'annual IS'!$G$8 -> 0.075630077 | X32: =X10/'quarterly IS'!$D$7 -> 0.14106253 | Y32: =Y10/'quarterly IS'!$D$7 -> 0.10815301 | Z32: =Z10/'quarterly IS'!$D$7 -> 0.13252299 | AA32: =AVERAGE(C32,H32,M32,R32,W32) -> 0.076080807 | AB32: =AA32 -> 0.076080807 | AC32: =AB32 -> 0.076080807 | AD32: =AC32 -> 0.076080807 | AE32: =AD32 -> 0.076080807
B33: Technology & Development – % of Revenue | C33: =C11/'annual IS'!$C$8 -> 0.17013918 | H33: =H11/'annual IS'!$D$8 -> 0.20800047 | I33: =I11/'annual IS'!I9 -> 531511.71 | J33: =J11/'annual IS'!J9 -> 581151.55 | K33: =K11/'annual IS'!K9 -> 898363.12 | L33: =L11/'annual IS'!L9 -> 944208.82 | M33: =M11/'annual IS'!$E$8 -> 0.22439855 | N33: =N11/'annual IS'!N9 -> #DIV/0! | O33: =O11/'annual IS'!O9 -> #DIV/0! | P33: =P11/'annual IS'!P9 -> #DIV/0! | Q33: =Q11/'annual IS'!Q9 -> #DIV/0! | R33: =R11/'annual IS'!$F$8 -> 0.21890141 | S33: =S11/'annual IS'!S9 -> #DIV/0! | T33: =T11/'annual IS'!T9 -> #DIV/0! | U33: =U11/'annual IS'!U9 -> #DIV/0! | V33: =V11/'annual IS'!V9 -> #DIV/0! | W33: =W11/'annual IS'!$G$8 -> 0.19963176 | X33: =X11/'quarterly IS'!$D$7 -> 0.33352515 | Y33: =Y11/'quarterly IS'!$D$7 -> 0.35180943 | Z33: =Z11/'quarterly IS'!$D$7 -> 0.35784628 | AA33: =AVERAGE(C33,H33,M33,R33,W33) -> 0.20421427 | AB33: =AA33 -> 0.20421427 | AC33: =AB33 -> 0.20421427 | AD33: =AC33 -> 0.20421427 | AE33: =AD33 -> 0.20421427
B34: General & Administrative – % of Revenue | C34: =C12/'annual IS'!$C$8 -> 0.11518056 | H34: =H12/'annual IS'!$D$8 -> 0.11153041 | I34: =I12/'annual IS'!I10 -> #DIV/0! | J34: =J12/'annual IS'!J10 -> #DIV/0! | K34: =K12/'annual IS'!K10 -> #DIV/0! | L34: =L12/'annual IS'!L10 -> #DIV/0! | M34: =M12/'annual IS'!$E$8 -> 0.11310963 | N34: =N12/'annual IS'!N10 -> #DIV/0! | O34: =O12/'annual IS'!O10 -> #DIV/0! | P34: =P12/'annual IS'!P10 -> #DIV/0! | Q34: =Q12/'annual IS'!Q10 -> #DIV/0! | R34: =R12/'annual IS'!$F$8 -> 0.10369883 | S34: =S12/'annual IS'!S10 -> #DIV/0! | T34: =T12/'annual IS'!T10 -> #DIV/0! | U34: =U12/'annual IS'!U10 -> #DIV/0! | V34: =V12/'annual IS'!V10 -> #DIV/0! | W34: =W12/'annual IS'!$G$8 -> 0.11023743 | X34: =X12/'quarterly IS'!$D$7 -> 0.13863042 | Y34: =Y12/'quarterly IS'!$D$7 -> 0.16281039 | Z34: =Z12/'quarterly IS'!$D$7 -> 0.16764205 | AA34: =AVERAGE(C34,H34,M34,R34,W34) -> 0.11075137 | AB34: =AA34 -> 0.11075137 | AC34: =AB34 -> 0.11075137 | AD34: =AC34 -> 0.11075137 | AE34: =AD34 -> 0.11075137
B35: Amortization of Acquired Intangibles – % of Revenue | C35: =C13/'annual IS'!$C$8 -> 0.10369017 | H35: =H13/'annual IS'!$D$8 -> 0.10943142 | I35: =I13/'annual IS'!I11 -> #DIV/0! | J35: =J13/'annual IS'!J11 -> #DIV/0! | K35: =K13/'annual IS'!K11 -> #DIV/0! | L35: =L13/'annual IS'!L11 -> #DIV/0! | M35: =M13/'annual IS'!$E$8 -> 0.10976063 | N35: =N13/'annual IS'!N11 -> #DIV/0! | O35: =O13/'annual IS'!O11 -> #DIV/0! | P35: =P13/'annual IS'!P11 -> #DIV/0! | Q35: =Q13/'annual IS'!Q11 -> #DIV/0! | R35: =R13/'annual IS'!$F$8 -> 0.092801327 | S35: =S13/'annual IS'!S11 -> #DIV/0! | T35: =T13/'annual IS'!T11 -> #DIV/0! | U35: =U13/'annual IS'!U11 -> #DIV/0! | V35: =V13/'annual IS'!V11 -> #DIV/0! | W35: =W13/'annual IS'!$G$8 -> 0.093249229 | X35: =X13/'quarterly IS'!$D$7 -> 0.14658907 | Y35: =Y13/'quarterly IS'!$D$7 -> 0.14658364 | Z35: =Z13/'quarterly IS'!$D$7 -> 0.14658907 | AA35: =AVERAGE(C35,H35,M35,R35,W35) -> 0.10178656 | AB35: =AA35 -> 0.10178656 | AC35: =AB35 -> 0.10178656 | AD35: =AC35 -> 0.10178656 | AE35: =AD35 -> 0.10178656
B37: Non-Operating Expense Drivers:
B38: Interest Expense (Income) – % of Debt | C38: =C18/('Balance Sheet'!C21+'Balance Sheet'!C25) -> -0.035350562 | D38: =D18/('Balance Sheet'!D21+'Balance Sheet'!D25) -> -0.0068794224 | E38: =E18/('Balance Sheet'!E21+'Balance Sheet'!E25) -> -0.0074508974 | F38: =F18/('Balance Sheet'!F21+'Balance Sheet'!F25) -> -0.01277439 | G38: =G18/('Balance Sheet'!#REF!+'Balance Sheet'!G25) -> #REF! | H38: =H18/('Balance Sheet'!H21+'Balance Sheet'!H25) -> -0.039289793 | I38: =I18/('Balance Sheet'!I21+'Balance Sheet'!I25) -> -0.011255019 | J38: =J18/('Balance Sheet'!J21+'Balance Sheet'!J25) -> -0.012383484 | K38: =K18/('Balance Sheet'!K21+'Balance Sheet'!K25) -> -0.013126956 | L38: =L18/('Balance Sheet'!L21+'Balance Sheet'!L25) -> -0.015459216 | M38: =M18/('Balance Sheet'!M21+'Balance Sheet'!M25) -> -0.052331148 | N38: =N18/('Balance Sheet'!N21+'Balance Sheet'!N25) -> #VALUE! | O38: =O18/('Balance Sheet'!O21+'Balance Sheet'!O25) -> #VALUE! | ... W38: =W18/('Balance Sheet'!W21+'Balance Sheet'!W25) -> -0.057402199 | AA38: =AVERAGE(C38,H38,M38,R38,W38) -> -0.049550574 | AB38: =AA38 -> -0.049550574 | AC38: =AB38 -> -0.049550574 | AD38: =AC38 -> -0.049550574 | AE38: =AD38 -> -0.049550574
B39: Provision for Income Taxes (Benefit) – Effective Tax Rate | C39: ='annual IS'!C36 -> -1.1338164 | D39: ='annual IS'!D36 -> 0.33640491 | E39: ='annual IS'!E36 -> 0.31375997 | F39: ='annual IS'!F36 -> 0.2575693 | G39: ='annual IS'!G36 -> 0.16659772 | H39: ='annual IS'!D36 -> 0.33640491 | I39: ='annual IS'!E36 -> 0.31375997 | J39: ='annual IS'!F36 -> 0.2575693 | K39: ='annual IS'!G36 -> 0.16659772 | L39: ='annual IS'!H36 -> 0.2424 | M39: ='annual IS'!E36 -> 0.31375997 | N39: ='annual IS'!J36 -> 0.248 | O39: ='annual IS'!K36 -> 0.25 | P39: ='annual IS'!L36 -> 0.25 | Q39: ='annual IS'!M36 -> 0 | R39: ='annual IS'!F36 -> 0.2575693 | S39: ='annual IS'!O36 -> 0 | T39: ='annual IS'!P36 -> 0 | U39: ='annual IS'!Q36 -> 0 | V39: ='annual IS'!R36 -> 0 | W39: ='annual IS'!G36 -> 0.16659772 | AA39: 0.2424 | AB39: 0.2486 | AC39: 0.248 | AD39: 0.25 | AE39: 0.25 | AF39: consensus effective tax rates
B41: Other income, net - % of rev | C41: ='annual IS'!C32/'annual IS'!C8 -> 0.0068255245 | D41: ='annual IS'!D32/'annual IS'!D8 -> -0.0078394726 | E41: ='annual IS'!E32/'annual IS'!E8 -> 0.0014749091 | F41: ='annual IS'!F32/'annual IS'!F8 -> 0.012801287 | G41: ='annual IS'!G32/'annual IS'!G8 -> 0.01194725 | H41: ='annual IS'!D32/'annual IS'!D8 -> -0.0078394726 | I41: ='annual IS'!I32/'annual IS'!I8 -> 0.004201583 | J41: ='annual IS'!J32/'annual IS'!J8 -> 0.004201583 | K41: ='annual IS'!K32/'annual IS'!K8 -> 0.004201583 | L41: ='annual IS'!L32/'annual IS'!L8 -> 0.004201583 | M41: ='annual IS'!E32/'annual IS'!E8 -> 0.0014749091 | N41: ='annual IS'!N32/'annual IS'!N8 -> #DIV/0! | O41: ='annual IS'!O32/'annual IS'!O8 -> #DIV/0! | P41: ='annual IS'!P32/'annual IS'!P8 -> #DIV/0! | Q41: ='annual IS'!Q32/'annual IS'!Q8 -> #DIV/0! | R41: ='annual IS'!F32/'annual IS'!F8 -> 0.012801287 | S41: ='annual IS'!S32/'annual IS'!S8 -> #DIV/0! | T41: ='annual IS'!T32/'annual IS'!T8 -> #DIV/0! | U41: ='annual IS'!U32/'annual IS'!U8 -> #DIV/0! | V41: ='annual IS'!V32/'annual IS'!V8 -> #DIV/0! | W41: ='annual IS'!G32/'annual IS'!G8 -> 0.01194725 | AA41: =AVERAGE(W41,R41,M41,H41,C41,) -> 0.004201583 | AB41: =AA41 -> 0.004201583 | AC41: =AB41 -> 0.004201583 | AD41: =AC41 -> 0.004201583 | AE41: =AD41 -> 0.004201583

Sheet Revenue Build
B1: Revenue Build - USD ($) in thousands | C1: Actual | X1: Estimated
C2: 2020A | D2: 2021 Q1 | E2: 2021 Q2 | F2: 2021 Q3 | G2: 2021 Q4 | H2: 2021A | I2: 2022 Q1 | J2: 2022 Q2 | K2: 2022 Q3 | L2: 2022 Q4 | M2: 2022A | N2: 2023 Q1 | O2: 2023 Q2 | P2: 2023 Q3 | Q2: 2023 Q4 | R2: 2023A | S2: 2024 Q1 | T2: 2024 Q2 | U2: 2024 Q3 | V2: 2024 Q4 | W2: 2024A | X2: 2025E | Y2: 2026E | Z2: 2027E | AA2: 2028E | AB2: 2029E
B3: Service Revenue | C3: ='quarterly IS'!C4 -> 430966 | D3: ='quarterly IS'!D4 -> 102534 | E3: ='quarterly IS'!E4 -> 109182 | F3: ='quarterly IS'!F4 -> 102733 | G3: ='quarterly IS'!G4 -> 112461 | H3: ='quarterly IS'!H4 -> 426910 | I3: ='quarterly IS'!I4 -> 104348 | J3: ='quarterly IS'!J4 -> 103034 | ... W3: ='quarterly IS'!W4 -> 478317 | X3: =X25*X28 -> 491352.42 | Y3: =Y25*Y28 -> 505600.02 | Z3: =Z25*Z28 -> 522131.77 | AA3: =AA25*AA28 -> 539980.28 | AB3: =AB25*AB28 -> 559558.64
B4: Custodial Revenue | C4: ='quarterly IS'!C5 -> 190933 | D4: ='quarterly IS'!D5 -> 46978 | E4: ='quarterly IS'!E5 -> 48776 | F4: ='quarterly IS'!F5 -> 49006 | G4: ='quarterly IS'!G5 -> 58057 | H4: ='quarterly IS'!H5 -> 202817 | I4: ='quarterly IS'!I5 -> 59365 | J4: ='quarterly IS'!J5 -> 65599 | ... W4: ='quarterly IS'!W5 -> 545414 | X4: =X52*1000 -> 662102.22 | Y4: =Y52*1000 -> 750965.44 | Z4: =Z52*1000 -> 838801.15 | AA4: =AA52*1000 -> 893208.91 | AB4: =AB52*1000 -> 951582.23
B5: Interchange Revenue | C5: ='quarterly IS'!C6 -> 111671 | D5: ='quarterly IS'!D6 -> 34690 | E5: ='quarterly IS'!E6 -> 31145 | F5: ='quarterly IS'!F6 -> 28215 | G5: ='quarterly IS'!G6 -> 32779 | H5: ='quarterly IS'!H6 -> 126829 | I5: ='quarterly IS'!I6 -> 41966 | J5: ='quarterly IS'!J6 -> 37509 | ... W5: ='quarterly IS'!W6 -> 176043 | X5: =X25*X67 -> 185908.66 | Y5: =Y25*Y67 -> 196655.06 | Z5: =Z25*Z67 -> 208765 | AA5: =AA25*AA67 -> 221933.57 | AB5: =AB25*AB67 -> 236399.35
A6: x | B6: Total Revenue | C6: =SUM(C3:C5) -> 733570 | D6: =SUM(D3:D5) -> 184202 | E6: =SUM(E3:E5) -> 189103 | F6: =SUM(F3:F5) -> 179954 | G6: =SUM(G3:G5) -> 203297 | H6: =SUM(H3:H5) -> 756556 | I6: =SUM(I3:I5) -> 205679 | J6: =SUM(J3:J5) -> 206142 | ... AB6: =SUM(AB3:AB5) -> 1747540.2
A9: x | B9: Revenue Drivers
B10: Service Revenue | E10: =(E3-D3)/D3 -> 0.06483703 | F10: =(F3-E3)/E3 -> -0.059066513 | G10: =(G3-F3)/F3 -> 0.094692066 | H10: =(H3-C3)/C3 -> -0.0094114153 | I10: =(I3-D3)/D3 -> 0.017691693 | J10: =(J3-E3)/E3 -> -0.056309648 | K10: =(K3-F3)/F3 -> 0.056914526 | L10: =(L3-G3)/G3 -> 0.2098772 | M10: =(M3-H3)/H3 -> 0.058832072 | N10: =(N3-I3)/I3 -> 0.064447809 | O10: =(O3-J3)/J3 -> 0.086631597 | ... W10: =(W3-R3)/R3 -> 0.04965437
B11: Custodial Revenue | E11: =(E4-D4)/D4 -> 0.038273234 | F11: =(F4-E4)/E4 -> 0.0047154338 | G11: =(G4-F4)/F4 -> 0.18469167 | H11: =(H4-C4)/C4 -> 0.062241729 | I11: =(I4-D4)/D4 -> 0.26367661 | J11: =(J4-E4)/E4 -> 0.34490323 | K11: =(K4-F4)/F4 -> 0.52311962 | L11: =(L4-G4)/G4 -> 0.062335291 | M11: =(M4-H4)/H4 -> 0.28826479 | N11: =(N4-I4)/I4 -> 0.4904405 | O11: =(O4-J4)/J4 -> 0.41276544 | ... W11: =(W4-R4)/R4 -> 0.41081858
B12: Interchange Revenue | E12: =(E5-D5)/D5 -> -0.10219083 | F12: =(F5-E5)/E5 -> -0.094076096 | G12: =(G5-F5)/F5 -> 0.16175793 | H12: =(H5-C5)/C5 -> 0.13573802 | I12: =(I5-D5)/D5 -> 0.20974344 | J12: =(J5-E5)/E5 -> 0.20433456 | K12: =(K5-F5)/F5 -> 0.16477051 | L12: =(L5-G5)/G5 -> 0.10134537 | M12: =(M5-H5)/H5 -> 0.17039478 | N12: =(N5-I5)/I5 -> 0.069413335 | O12: =(O5-J5)/J5 -> 0.037431017 | ... W12: =(W5-R5)/R5 -> 0.11913314
A15: x | B15: Service Revenue
B16: Total HSA Accounts (Equity Research) | C16: 30200 | H16: 32500 | M16: 35500 | R16: 37400 | W16: 39300 | X16: =W16*(1+X17) -> 41265 | Y16: =X16*(1+Y17) -> 43328.25 | Z16: =Y16*(1+Z17) -> 45537.991 | AA16: =Z16*(1+AA17) -> 47860.428 | AB16: =AA16*(1+AB17) -> 50349.171
B17: Growth Rate | H17: =H16/C16-1 -> 0.07615894 | I17: =I16/D16-1 -> #DIV/0! | J17: =J16/E16-1 -> #DIV/0! | K17: =K16/F16-1 -> #DIV/0! | L17: =L16/G16-1 -> #DIV/0! | M17: =M16/H16-1 -> 0.092307692 | N17: =N16/I16-1 -> #DIV/0! | O17: =O16/J16-1 -> #DIV/0! | ... W17: =W16/R16-1 -> 0.050802139 | X17: 0.05 | Y17: 0.05 | Z17: 0.051 | AA17: 0.051 | AB17: 0.052
B18: HQY HSA Market Share (%) | C18: =C21/C16 -> 0.19145695 | D18: =D21/D16 -> #DIV/0! | E18: =E21/E16 -> #DIV/0! | F18: =F21/F16 -> #DIV/0! | G18: =G21/G16 -> #DIV/0! | H18: =H21/H16 -> 0.22175385 | I18: =I21/I16 -> #DIV/0! | J18: =J21/J16 -> #DIV/0! | ... W18: =W21/W16 -> 0.2516285 | X18: 0.255 | Y18: =X18+$AC18 -> 0.256 | Z18: =Y18+$AC18 -> 0.257 | AA18: =Z18+$AC18 -> 0.258 | AB18: =AA18+$AC18 -> 0.259 | AC18: 0.001 | AD18: (+)
A20: x | B20: Accounts
B21: HSAs | C21: 5782 | D21: 5846 | E21: 5972 | F21: 6241 | G21: 7207 | H21: =G21 -> 7207 | I21: 7359 | J21: 7523 | K21: 7650 | L21: 7984 | M21: =L21 -> 7984 | N21: 8045 | O21: 8164 | P21: 8295 | Q21: 8692 | R21: =Q21 -> 8692 | S21: 9097 | T21: 9383 | U21: 9508 | V21: 9889 | W21: =V21 -> 9889 | X21: =X16*X18 -> 10522.575 | Y21: =Y16*Y18 -> 11092.032 | Z21: =Z16*Z18 -> 11703.264 | AA21: =AA16*AA18 -> 12347.99 | AB21: =AB16*AB18 -> 13040.435
B22: % growth rate | E22: =(E21-D21)/D21 -> 0.021553199 | F22: =(F21-E21)/E21 -> 0.045043537 | G22: =(G21-F21)/F21 -> 0.15478289 | H22: =(H21-C21)/C21 -> 0.24645451 | I22: =(I21-D21)/D21 -> 0.25880944 | J22: =(J21-E21)/E21 -> 0.25971199 | K22: =(K21-F21)/F21 -> 0.2257651 | L22: =(L21-G21)/G21 -> 0.10781185 | M22: =(M21-H21)/H21 -> 0.10781185 | N22: =(N21-I21)/I21 -> 0.093219187 | O22: =(O21-J21)/J21 -> 0.08520537 | ... W22: =(W21-R21)/R21 -> 0.13771284 | X22: =X21/W21-1 -> 0.064068662 | Y22: =Y21/X21-1 -> 0.054117647 | Z22: =Z21/Y21-1 -> 0.055105469 | AA22: =AA21/Z21-1 -> 0.055089494 | AB22: =AB21/AA21-1 -> 0.056077519
B23: CDBs | C23: 7028 | D23: 6986 | E23: 7171 | F23: 7085 | G23: 7192 | H23: =G23 -> 7192 | I23: 7095 | J23: 7023 | K23: 6849 | L23: 6933 | M23: =L23 -> 6933 | N23: 6954 | O23: 6831 | P23: 6984 | Q23: 7006 | R23: =Q23 -> 7006 | S23: 6913 | T23: 6898 | U23: 6955 | V23: 7144 | W23: =V23 -> 7144 | X23: =W23*(1+X24) -> 7286.88 | Y23: =X23*(1+Y24) -> 7541.9208 | Z23: =Y23*(1+Z24) -> 7843.5976 | AA23: =Z23*(1+AA24) -> 8165.1851 | AB23: =AA23*(1+AB24) -> 8508.1229
B24: % growth rate | H24: =H23/C23-1 -> 0.023335231 | I24: =I23/D23-1 -> 0.015602634 | J24: =J23/E23-1 -> -0.020638684 | K24: =K23/F23-1 -> -0.033309809 | L24: =L23/G23-1 -> -0.036012236 | M24: =M23/H23-1 -> -0.036012236 | N24: =N23/I23-1 -> -0.01987315 | O24: =O23/J23-1 -> -0.027338744 | ... W24: =W23/R23-1 -> 0.019697402 | X24: 0.02 | Y24: 0.035 | Z24: 0.04 | AA24: =Z24+$AC24 -> 0.041 | AB24: =AA24+$AC24 -> 0.042 | AC24: 0.001 | AD24: (+)
B25: Totals | C25: =SUM(C23,C21) -> 12810 | D25: =SUM(D23,D21) -> 12832 | E25: =SUM(E23,E21) -> 13143 | F25: =SUM(F23,F21) -> 13326 | G25: =SUM(G23,G21) -> 14399 | H25: =SUM(H23,H21) -> 14399 | I25: =SUM(I23,I21) -> 14454 | J25: =SUM(J23,J21) -> 14546 | ... AB25: =SUM(AB23,AB21) -> 21548.558
B26: Growth Rate | H26: =H25/C25-1 -> 0.12404372 | I26: =I25/D25-1 -> 0.12640274 | J26: =J25/E25-1 -> 0.10674884 | K26: =K25/F25-1 -> 0.088023413 | L26: =L25/G25-1 -> 0.03597472 | M26: =M25/H25-1 -> 0.03597472 | N26: =N25/I25-1 -> 0.037705825 | O26: =O25/J25-1 -> 0.030867592 | ... W26: =W25/R25-1 -> 0.085042681 | X26: =X25/W25-1 -> 0.045585334 | Y26: =Y25/X25-1 -> 0.04629551 | Z26: =Z25/Y25-1 -> 0.048991669 | AA26: =AA25/Z25-1 -> 0.049435782 | AB26: =AB25/AA25-1 -> 0.050474021
B28: Service Revenue Per Acct. | C28: =C3/C25 -> 33.642935 | D28: =D3/D25 -> 7.9904925 | E28: =E3/E25 -> 8.3072358 | F28: =F3/F25 -> 7.7092151 | G28: =G3/G25 -> 7.8103341 | H28: =H3/H25 -> 29.648587 | I28: =I3/I25 -> 7.2193165 | J28: =J3/J25 -> 7.0833219 | ... W28: =W3/W25 -> 28.081782 | X28: =W28*(1+X29) -> 27.589414 | Y28: =X28*(1+Y29) -> 27.133267 | Z28: =Y28*(1+Z29) -> 26.711796 | AA28: =Z28*(1+AA29) -> 26.323583 | AB28: =AA28*(1+AB29) -> 25.967336
B29: Growth Rate | H29: =H28/C28-1 -> -0.11872771 | I29: =I28/D28-1 -> -0.096511706 | J29: =J28/E28-1 -> -0.14733107 | K29: =K28/F28-1 -> -0.028592112 | L29: =L28/G28-1 -> 0.16786363 | M29: =M28/H28-1 -> 0.022063619 | N29: =N28/I28-1 -> 0.025770294 | O29: =O28/J28-1 -> 0.054094246 | ... W29: =W28/R28-1 -> -0.032614671 | X29: =AVERAGE(M29,R29,W29) -> -0.017533386 | Y29: =X29+$AC29 -> -0.016533386 | Z29: =Y29+$AC29 -> -0.015533386 | AA29: =Z29+$AC29 -> -0.014533386 | AB29: =AA29+$AC29 -> -0.013533386 | AC29: 0.001 | AD29: (-)
E31: =(E25-D25)/D25 -> 0.024236284 | F31: =(F25-E25)/E25 -> 0.013923762 | G31: =(G25-F25)/F25 -> 0.080519286 | I31: =(I25-G25)/G25 -> 0.0038197097 | J31: =(J25-I25)/I25 -> 0.0063650201 | K31: =(K25-J25)/J25 -> -0.0032311288 | L31: =(L25-K25)/K25 -> 0.028829574 | N31: =(N25-L25)/L25 -> 0.0054970839 | O31: =(O25-N25)/N25 -> -0.00026668445 | P31: =(P25-O25)/O25 -> 0.018939647 | Q31: =(Q25-P25)/P25 -> 0.027423261 | S31: =(S25-Q25)/Q25 -> 0.019875143 | T31: =(T25-S25)/S25 -> 0.016926921 | U31: =(U25-T25)/T25 -> 0.011178675 | V31: =(V25-U25)/U25 -> 0.034623094
A32: x | B32: Custodial Revenue
B33: Average Annualized Yield on HSA Cash | C33: =(C42/C50/12)/100 -> 0.039714939 | D33: =(D42/D50/12)/100 -> 0 | E33: =(E42/E50/12)/100 -> 0 | F33: =(F42/F50/12)/100 -> 0 | G33: =(G42/G50/12)/100 -> 0 | H33: =(H42/H50/12)/100 -> 0.045501092 | I33: =(I42/I50/12)/100 -> 0 | J33: =(J42/J50/12)/100 -> 0 | ... W33: =(W42/W50/12)/100 -> 0.026202124 | X33: 0.035 | Y33: 0.0375 | Z33: 0.0395 | AA33: 0.0395 | AB33: 0.0395
B34: Average Annualized Fee on HSA Investments | C34: =(C44/C51/12)/100 -> 0.067213804 | D34: =(D44/D51/12)/100 -> 0 | E34: =(E44/E51/12)/100 -> 0 | F34: =(F44/F51/12)/100 -> 0 | G34: =(G44/G51/12)/100 -> 0 | H34: =(H44/H51/12)/100 -> 0.062901905 | I34: =(I44/I51/12)/100 -> 0 | J34: =(J44/J51/12)/100 -> 0 | ... W34: =(W44/W51/12)/100 -> 0.022696132 | X34: =AVERAGE(H34,M34,R34,W34) -> 0.041668139 | Y34: 0.041668139 | Z34: 0.041668139 | AA34: 0.041668139 | AB34: 0.041668139
B36: HSA Assets
B37: Cash | C37: 10119 | D37: 10026 | E37: 10028 | F37: 10469 | G37: 12943 | H37: =G37 -> 12943 | I37: 12935 | J37: 13097 | K37: 13096 | L37: 14199 | M37: =L37 -> 14199 | N37: 14113 | O37: 14021 | P37: 13971 | Q37: 15006 | R37: =Q37 -> 15006 | S37: 15850 | T37: 16368 | U37: 16386 | V37: 17435 | W37: =V37 -> 17435 | X37: =X55*X21 -> 18591.155 | Y37: =Y55*Y21 -> 19638.587 | Z37: =Z55*Z21 -> 20764.471 | AA37: =AA55*AA21 -> 21954.57 | AB37: =AB55*AB21 -> 23234.617
B38: Cash growth rate | E38: =(E37-D37)/D37 -> 0.00019948135 | F38: =(F37-E37)/E37 -> 0.043976865 | G38: =(G37-F37)/F37 -> 0.23631674 | H38: =(H37-C37)/C37 -> 0.27907896 | I38: =(I37-D37)/D37 -> 0.29014562 | J38: =(J37-E37)/E37 -> 0.30604308 | K38: =(K37-F37)/F37 -> 0.25093132 | L38: =(L37-G37)/G37 -> 0.097040872 | M38: =(M37-H37)/H37 -> 0.097040872 | N38: =(N37-I37)/I37 -> 0.091070738 | O38: =(O37-J37)/J37 -> 0.070550508 | ... W38: =(W37-R37)/R37 -> 0.16186859 | X38: =X37/W37-1 -> 0.06631231 | Y38: =Y37/X37-1 -> 0.056340313 | Z38: =Z37/Y37-1 -> 0.057330217 | AA38: =AA37/Z37-1 -> 0.057314209 | AB38: =AB37/AA37-1 -> 0.058304318
B39: Investments | C39: 4216 | D39: 4987 | E39: 5443 | F39: 5959 | G39: 6675 | H39: =G39 -> 6675 | I39: 7330 | J39: 7441 | K39: 7108 | L39: 7947 | M39: =L39 -> 7947 | N39: 8206 | O39: 9181 | P39: 8597 | Q39: 10208 | R39: =Q39 -> 10208 | S39: 11427 | T39: 13099 | U39: 13601 | V39: 14676 | W39: =V39 -> 14676 | X39: =X57*X21 -> 17334.062 | Y39: =Y57*Y21 -> 20099.354 | Z39: =Z57*Z21 -> 23115.563 | AA39: =AA57*AA21 -> 26340.107 | AB39: =AB57*AB21 -> 29764.398
B40: Investments growth rate | E40: =(E39-D39)/D39 -> 0.091437738 | F40: =(F39-E39)/E39 -> 0.094800661 | G40: =(G39-F39)/F39 -> 0.12015439 | H40: =(H39-C39)/C39 -> 0.58325427 | I40: =(I39-D39)/D39 -> 0.46982154 | J40: =(J39-E39)/E39 -> 0.36707698 | K40: =(K39-F39)/F39 -> 0.19281759 | L40: =(L39-G39)/G39 -> 0.1905618 | M40: =(M39-H39)/H39 -> 0.1905618 | N40: =(N39-I39)/I39 -> 0.11950887 | O40: =(O39-J39)/J39 -> 0.23383954 | ... W40: =(W39-R39)/R39 -> 0.43769592 | X40: =X39/W39-1 -> 0.18111621 | Y40: =Y39/X39-1 -> 0.15952941 | Z40: =Z39/Y39-1 -> 0.15006496 | AA40: =AA39/Z39-1 -> 0.13949665 | AB40: =AB39/AA39-1 -> 0.13000295
B41: Total Assets | C41: =SUM(C37:C39) -> 14335 | D41: =SUM(D37:D39) -> 15013 | E41: =SUM(E37:E39) -> 15471 | F41: =SUM(F37:F39) -> 16428.044 | G41: =SUM(G37:G39) -> 19618.236 | H41: =SUM(H37:H39) -> 19618.279 | I41: =SUM(I37:I39) -> 20265.29 | J41: =SUM(J37:J39) -> 20538.306 | ... AB41: =SUM(AB37:AB39) -> 52999.073
B42: Average Daily HSA Cash During Period | C42: 8599 | H42: 10465 | M42: 13049 | R42: 14071 | W42: 16206 | X42: =X37*X43 -> 17266.285 | Y42: =Y37*Y43 -> 18239.073 | Z42: =Z37*Z43 -> 19284.723 | AA42: =AA37*AA43 -> 20390.011 | AB42: =AB37*AB43 -> 21578.837
B43: % of Total HSA Cash | C43: =C42/C37 -> 0.84978753 | D43: =D42/D37 -> 0 | E43: =E42/E37 -> 0 | F43: =F42/F37 -> 0 | G43: =G42/G37 -> 0 | H43: =H42/H37 -> 0.80854516 | I43: =I42/I37 -> 0 | J43: =J42/J37 -> 0 | ... W43: =W42/W37 -> 0.92950961 | X43: =AVERAGE(M43,R43,W43) -> 0.92873653 | Y43: 0.92873653 | Z43: 0.92873653 | AA43: 0.92873653 | AB43: 0.92873653
B44: Average Daily Client-Held Funds During Period | C44: 847 | H44: 842 | M44: 827 | R44: 845 | W44: 817 | X44: =X39*X45 -> 1386.7249 | Y44: =Y39*Y45 -> 1607.9483 | Z44: =Z39*Z45 -> 1849.245 | AA44: =AA39*AA45 -> 2107.2085 | AB44: =AB39*AB45 -> 2381.1519
B45: % of Total HSA Investments | C45: =C44/C39 -> 0.20090133 | D45: =D44/D39 -> 0 | E45: =E44/E39 -> 0 | F45: =F44/F39 -> 0 | G45: =G44/G39 -> 0 | H45: =H44/H39 -> 0.12614232 | I45: =I44/I39 -> 0 | J45: =J44/J39 -> 0 | ... W45: =W44/W39 -> 0.05566912 | X45: 0.08 | Y45: 0.08 | Z45: 0.08 | AA45: 0.08 | AB45: 0.08
B47: % Cash | C47: =C37/C41 -> 0.70589466 | D47: =D37/D41 -> 0.66782122 | E47: =E37/E41 -> 0.64818046 | F47: =F37/F41 -> 0.63726394 | G47: =G37/G41 -> 0.6597433 | H47: =H37/H41 -> 0.65974186 | I47: =I37/I41 -> 0.63828348 | J47: =J37/J41 -> 0.63768648 | ... AB47: =AB37/AB41 -> 0.43839666
B48: % Investment | C48: =C39/C41 -> 0.29410534 | D48: =D39/D41 -> 0.33217878 | E48: =E39/E41 -> 0.35181953 | F48: =F39/F41 -> 0.36273338 | G48: =G39/G41 -> 0.34024465 | H48: =H39/H41 -> 0.34024391 | I48: =I39/I41 -> 0.3617022 | J48: =J39/J41 -> 0.36229862 | ... AB48: =AB39/AB41 -> 0.56160224
B50: Estimtated Custodial Revs. From Yield On Cash (~94.5% of Custodial rev.) | C50: =(C4/1000)*0.945 -> 180.43168 | D50: =(D4/1000)*0.945 -> 44.39421 | E50: =(E4/1000)*0.945 -> 46.09332 | F50: =(F4/1000)*0.945 -> 46.31067 | G50: =(G4/1000)*0.945 -> 54.863865 | H50: =(H4/1000)*0.945 -> 191.66206 | I50: =(I4/1000)*0.945 -> 56.099925 | J50: =(J4/1000)*0.945 -> 61.991055 | ... W50: =(W4/1000)*0.945 -> 515.41623 | X50: =X33*X42 -> 604.31997 | Y50: =Y33*Y42 -> 683.96523 | Z50: =Z33*Z42 -> 761.74655 | AA50: =AA33*AA42 -> 805.40545 | AB50: =AB33*AB42 -> 852.36406
B51: Other Custodial Revenues | C51: =(C4/1000)-C50 -> 10.501315 | D51: =(D4/1000)-D50 -> 2.58379 | E51: =(E4/1000)-E50 -> 2.68268 | F51: =(F4/1000)-F50 -> 2.69533 | G51: =(G4/1000)-G50 -> 3.193135 | H51: =(H4/1000)-H50 -> 11.154935 | I51: =(I4/1000)-I50 -> 3.265075 | J51: =(J4/1000)-J50 -> 3.607945 | ... W51: =(W4/1000)-W50 -> 29.99777 | X51: =X34*X44 -> 57.782246 | Y51: =Y34*Y44 -> 67.000214 | Z51: =Z34*Z44 -> 77.054599 | AA51: =AA34*AA44 -> 87.803457 | AB51: =AB34*AB44 -> 99.218165
B52: Total Custodial Revenues | C52: =SUM(C50:C51) -> 190.933 | D52: =SUM(D50:D51) -> 46.978 | E52: =SUM(E50:E51) -> 48.776 | F52: =SUM(F50:F51) -> 49.006 | G52: =SUM(G50:G51) -> 58.057 | H52: =SUM(H50:H51) -> 202.817 | I52: =SUM(I50:I51) -> 59.365 | J52: =SUM(J50:J51) -> 65.599 | ... AB52: =SUM(AB50:AB51) -> 951.58223
B55: cash per account | C55: =C37/C21 -> 1.7500865 | D55: =D37/D21 -> 1.7150188 | E55: =E37/E21 -> 1.6791695 | F55: =F37/F21 -> 1.6774555 | G55: =G37/G21 -> 1.7958929 | H55: =H37/H21 -> 1.7958929 | I55: =I37/I21 -> 1.7577116 | J55: =J37/J21 -> 1.7409278 | ... W55: =W37/W21 -> 1.7630701 | X55: =W55*(1+X56) -> 1.7667876 | Y55: =X55*(1+Y56) -> 1.770513 | Z55: =Y55*(1+Z56) -> 1.7742462 | AA55: =Z55*(1+AA56) -> 1.7779873 | AB55: =AA55*(1+AB56) -> 1.7817363
B56: growth rate | E56: =(E55-D55)/D55 -> -0.020903187 | F56: =(F55-E55)/E55 -> -0.001020696 | G56: =(G55-F55)/F55 -> 0.070605356 | H56: =(H55-C55)/C55 -> 0.026173796 | I56: =(I55-D55)/D55 -> 0.024893505 | J56: =(J55-E55)/E55 -> 0.036779113 | K56: =(K55-F55)/F55 -> 0.020531029 | L56: =(L55-G55)/G55 -> -0.0097227504 | M56: =(M55-H55)/H55 -> -0.0097227504 | N56: =(N55-I55)/I55 -> -0.0019652501 | O56: =(O55-J55)/J55 -> -0.01350423 | ... W56: =(W55-R55)/R55 -> 0.021231848 | X56: =AVERAGE(H56,M56,R56,W56) -> 0.0021085557 | Y56: 0.0021085557 | Z56: 0.0021085557 | AA56: 0.0021085557 | AB56: 0.0021085557
B57: investment per account | C57: =C39/C21 -> 0.72915946 | D57: =D39/D21 -> 0.85306192 | E57: =E39/E21 -> 0.91141996 | F57: =F39/F21 -> 0.95481493 | G57: =G39/G21 -> 0.92618288 | H57: =H39/H21 -> 0.92618288 | I57: =I39/I21 -> 0.99605925 | J57: =J39/J21 -> 0.98910009 | ... W57: =W39/W21 -> 1.4840732 | X57: =W57*(1+X58) -> 1.6473213 | Y57: =X57*(1+Y58) -> 1.8120534 | Z57: =Y57*(1+Z58) -> 1.9751382 | AA57: =Z57*(1+AA58) -> 2.1331493 | AB57: =AA57*(1+AB58) -> 2.2824697
B58: growth rate | E58: =(E57-D57)/D57 -> 0.068410083 | F58: =(F57-E57)/E57 -> 0.04761249 | G58: =(G57-F57)/F57 -> -0.029987021 | H58: =(H57-C57)/C57 -> 0.27020621 | I58: =(I57-D57)/D57 -> 0.16762831 | J58: =(J57-E57)/E57 -> 0.085229792 | K58: =(K57-F57)/F57 -> -0.026879143 | L58: =(L57-G57)/G57 -> 0.074696753 | M58: =(M57-H57)/H57 -> 0.074696753 | N58: =(N57-I57)/I57 -> 0.02404795 | O58: =(O57-J57)/J57 -> 0.13696409 | ... W58: =(W57-R57)/R57 -> 0.26367206 | X58: 0.11 | Y58: =X58-$AC58 -> 0.1 | Z58: =Y58-$AC58 -> 0.09 | AA58: =Z58-$AC58 -> 0.08 | AB58: =AA58-$AC58 -> 0.07 | AC58: 0.01 | AD58: (-)
B60: Total Revenue | C60: =C6 -> 733570 | D60: =D6 -> 184202 | E60: =E6 -> 189103 | F60: =F6 -> 179954 | G60: =G6 -> 203297 | H60: =SUM(D60:G60) -> 756556 | I60: =I6 -> 205679 | J60: =J6 -> 206142 | K60: =K6 -> 216086 | L60: =L6 -> 233841 | M60: =SUM(I60:L60) -> 861748 | N60: =N6 -> 244432 | O60: =O6 -> 243549 | P60: =P6 -> 249219 | Q60: =Q6 -> 262387 | R60: =SUM(N60:Q60) -> 999587 | S60: =S6 -> 287597 | T60: =T6 -> 299928 | U60: =U6 -> 300432 | V60: =V6 -> 311817 | W60: =SUM(S60:V60) -> 1199774
B61: % Service Revenue | C61: =C3/$C$60 -> 0.58749131 | D61: =D3/$D$60 -> 0.55663891 | E61: =E3/$E$60 -> 0.57736789 | F61: =F3/$F$60 -> 0.57088478 | G61: =G3/$G$60 -> 0.55318573 | H61: =H3/$H$60 -> 0.56428077 | I61: =I3/$I$60 -> 0.50733424 | J61: =J3/$J$60 -> 0.49982051 | K61: =K3/$K$60 -> 0.50248512 | L61: =L3/$L$60 -> 0.58186546 | M61: =M3/$H$60 -> 0.59747857 | N61: =N3/$N$60 -> 0.45441268 | O61: =O3/$O$60 -> 0.45970215 | P61: =P3/$P$60 -> 0.45775804 | Q61: =Q3/$Q$60 -> 0.45190882 | R61: =R3/$H$60 -> 0.60232157 | S61: =S3/$S$60 -> 0.41104045 | T61: =T3/$T$60 -> 0.38916007 | U61: =U3/$U$60 -> 0.39667545 | V61: =V3/$V$60 -> 0.39833941 | W61: =W3/$H$60 -> 0.63222947
B62: % Custodial Revenue | C62: =C4/$C$60 -> 0.26027918 | D62: =D4/$D$60 -> 0.25503523 | E62: =E4/$E$60 -> 0.25793351 | F62: =F4/$F$60 -> 0.27232515 | G62: =G4/$G$60 -> 0.28557726 | H62: =H4/$H$60 -> 0.2680793 | I62: =I4/$I$60 -> 0.28862937 | J62: =J4/$J$60 -> 0.31822239 | K62: =K4/$K$60 -> 0.34542728 | L62: =L4/$L$60 -> 0.26375187 | M62: =M4/$H$60 -> 0.34535712 | N62: =N4/$N$60 -> 0.36198206 | O62: =O4/$O$60 -> 0.38052302 | P62: =P4/$P$60 -> 0.40127358 | Q62: =Q4/$Q$60 -> 0.4018225 | R62: =R4/$H$60 -> 0.51099192 | S62: =S4/$S$60 -> 0.42296686 | T62: =T4/$T$60 -> 0.46239097 | U62: =U4/$U$60 -> 0.46916773 | V62: =V4/$V$60 -> 0.46223586 | W62: =W4/$H$60 -> 0.72091689
B63: % Interchange Revenue | C63: =C5/$C$60 -> 0.15222951 | D63: =D5/$D$60 -> 0.18832586 | E63: =E5/$E$60 -> 0.1646986 | F63: =F5/$F$60 -> 0.15679007 | G63: =G5/$G$60 -> 0.16123701 | H63: =H5/$H$60 -> 0.16763994 | I63: =I5/$I$60 -> 0.20403639 | J63: =J5/$J$60 -> 0.1819571 | K63: =K5/$K$60 -> 0.15208759 | L63: =L5/$L$60 -> 0.15438268 | M63: =M5/$H$60 -> 0.19620491 | N63: =N5/$N$60 -> 0.18360526 | O63: =O5/$O$60 -> 0.15977483 | P63: =P5/$P$60 -> 0.14096839 | Q63: =Q5/$Q$60 -> 0.14626868 | R63: =R5/$H$60 -> 0.20791984 | S63: =S5/$S$60 -> 0.16599269 | T63: =T5/$T$60 -> 0.14844896 | U63: =U5/$U$60 -> 0.13415681 | V63: =V5/$V$60 -> 0.13942473 | W63: =W5/$H$60 -> 0.23268998
A66: x | B66: Interchange revenue
B67: Spend per account | C67: =C5/C25 -> 8.7174863 | D67: =D5/D25 -> 2.7033978 | E67: =E5/E25 -> 2.3697025 | F67: =F5/F25 -> 2.1172895 | G67: =G5/G25 -> 2.2764775 | H67: =H5/H25 -> 8.8081811 | I67: =I5/I25 -> 2.9034177 | J67: =J5/J25 -> 2.5786471 | ... W67: =W5/W25 -> 10.335408 | X67: =W67*(1+X68) -> 10.438762 | Y67: =X67*(1+Y68) -> 10.553588 | Z67: =Y67*(1+Z68) -> 10.680231 | AA67: =Z67*(1+AA68) -> 10.819074 | AB67: =AA67*(1+AB68) -> 10.970541
B68: Growth Rate | H68: =H67/C67-1 -> 0.010403777 | I68: =I67/D67-1 -> 0.073988366 | J68: =J67/E67-1 -> 0.088173324 | K68: =K67/F67-1 -> 0.070538095 | L68: =L67/G67-1 -> 0.063100626 | M68: =M67/H67-1 -> 0.12975226 | N68: =N67/I67-1 -> 0.030555393 | O68: =O67/J67-1 -> 0.0063668934 | ... W68: =W67/R67-1 -> 0.03141854 | X68: 0.01 | Y68: =X68+$AC68 -> 0.011 | Z68: =Y68+$AC68 -> 0.012 | AA68: =Z68+$AC68 -> 0.013 | AB68: =AA68+$AC68 -> 0.014 | AC68: 0.001 | AD68: (+)

Sheet Balance Sheet Build
B1: Balance Sheet Build- USD($) in thousands | C1: Actual | H1: Expected
C2: 2020 | D2: =C2+1 -> 2021 | E2: =D2+1 -> 2022 | F2: =E2+1 -> 2023 | G2: =F2+1 -> 2024 | H2: =G2+1 -> 2025 | I2: =H2+1 -> 2026 | J2: =I2+1 -> 2027 | K2: =J2+1 -> 2028 | L2: =K2+1 -> 2029
A3: x | B3: Assets
B5: Receivables, net - % of revenue | C5: ='Balance Sheet'!C6/'annual IS'!C8 -> 0.099195714 | D5: ='Balance Sheet'!H6/'annual IS'!D8 -> 0.11556051 | E5: ='Balance Sheet'!M6/'annual IS'!E8 -> 0.11237044 | F5: ='Balance Sheet'!R6/'annual IS'!F8 -> 0.10493634 | G5: ='Balance Sheet'!W6/'annual IS'!G8 -> 0.098356857 | H5: =AVERAGE(C5,D5,E5,F5,G5) -> 0.10608397 | I5: =H5 -> 0.10608397 | J5: =I5 -> 0.10608397 | K5: =J5 -> 0.10608397 | L5: =K5 -> 0.10608397
B7: Prepaid expenses & other current assets – % of revenue | C7: ='Balance Sheet'!C7/'annual IS'!C8 -> 0.079892853 | D7: ='Balance Sheet'!H7/'annual IS'!D8 -> 0.050881891 | E7: ='Balance Sheet'!M7/'annual IS'!E8 -> 0.036892456 | F7: ='Balance Sheet'!R7/'annual IS'!F8 -> 0.048584065 | G7: ='Balance Sheet'!W7/'annual IS'!G8 -> 0.053172514 | H7: =AVERAGE(E7,F7,G7) -> 0.046216345 | I7: =H7 -> 0.046216345 | J7: =I7 -> 0.046216345 | K7: =J7 -> 0.046216345 | L7: =K7 -> 0.046216345
B9: Operating lease ROU assets – % of revenue | C9: ='Balance Sheet'!C10/'annual IS'!C8 -> 0.12201699 | D9: ='Balance Sheet'!H10/'annual IS'!D8 -> 0.084082342 | E9: ='Balance Sheet'!M10/'annual IS'!E8 -> 0.065519154 | F9: ='Balance Sheet'!R10/'annual IS'!F8 -> 0.048399989 | G9: ='Balance Sheet'!W10/'annual IS'!G8 -> 0.035994279 | H9: =G9-$M$9 -> 0.033494279 | I9: =H9-$M$9 -> 0.030994279 | J9: =I9-$M$9 -> 0.028494279 | K9: =J9-$M$9 -> 0.025994279 | L9: =K9-$M$9 -> 0.023494279 | M9: 0.0025 | N9: (-)
B11: Other assets - % of revenue | C11: ='Balance Sheet'!C13/'annual IS'!C8 -> 0.05101081 | D11: ='Balance Sheet'!H13/'annual IS'!D8 -> 0.065833858 | E11: ='Balance Sheet'!M13/'annual IS'!E8 -> 0.060551344 | F11: ='Balance Sheet'!R13/'annual IS'!F8 -> 0.067896041 | G11: ='Balance Sheet'!W13/'annual IS'!G8 -> 0.059656235 | H11: 0.07 | I11: =H11+$M$11 -> 0.071 | J11: =I11+$M$11 -> 0.072 | K11: =J11+$M$11 -> 0.073 | L11: =K11+$M$11 -> 0.074 | M11: 0.001 | N11: (+)
A13: x | B13: PPE
B14: BOY PPE | G14: =F17 -> 6013 | H14: =G17 -> 3239 | I14: =H17 -> 1434.7951 | J14: =I17 -> 567.13293 | K14: =J17 -> 807.19999 | L14: =K17 -> 2301.6739
B15: Plus: Capex | C15: 13090 | D15: 8910 | E15: 3371 | F15: 1694 | G15: 2084 | H15: =H27*'annual IS'!H8 -> 2661.3066 | I15: =I27*'annual IS'!I8 -> 3250.8453 | J15: =J27*'annual IS'!J8 -> 3903.829 | K15: =K27*'annual IS'!K8 -> 4530.0607 | L15: =L27*'annual IS'!L8 -> 5219.8918
B16: Less: Depreciation Expense | C16: 16000 | D16: 14700 | E16: 12300 | F16: 8800 | G16: 4600 | H16: =H26*'annual IS'!H8 -> 4465.5114 | I16: =I26*'annual IS'!I8 -> 4118.5075 | J16: =J26*'annual IS'!J8 -> 3663.7619 | K16: =K26*'annual IS'!K8 -> 3035.5869 | L16: =L26*'annual IS'!L8 -> 2331.3155 | O16: from IS
A17: x | B17: EOY PPE | F17: ='Balance Sheet'!R9 -> 6013 | G17: ='Balance Sheet'!W9 -> 3239 | H17: =H14+H15-H16 -> 1434.7951 | I17: =I14+I15-I16 -> 567.13293 | J17: =J14+J15-J16 -> 807.19999 | K17: =K14+K15-K16 -> 2301.6739 | L17: =L14+L15-L16 -> 5190.2502
B19: Intangible assets
B20: Intangible assets, gross | F20: 1437450 | G20: 1954752 | H20: =G20 -> 1954752 | I20: =H20 -> 1954752 | J20: =I20 -> 1954752 | K20: =J20 -> 1954752 | L20: =K20 -> 1954752
B21: Less: Accumulated amortization | C21: 195749 | D21: 316717 | E21: 463530 | F21: 601502 | G21: 750094 | H21: =G21+H24 -> 896603 | I21: =H21+I24 -> 1026203.5 | J21: =I21+J24 -> 1137847.5 | K21: =J21+K24 -> 1236002.5 | L21: =K21+L24 -> 1333132.5
B22: Intangible assets, net | F22: =F20-F21 -> 835948 | G22: =G20-G21 -> 1204658 | H22: =H20-H21 -> 1058149 | I22: =I20-I21 -> 928548.47 | J22: =J20-J21 -> 816904.47 | K22: =K20-K21 -> 718749.47 | L22: =L20-L21 -> 621619.47
B24: Amortization expense | H24: =146511-2 -> 146509 | I24: =129812-211.469122753479 -> 129600.53 | J24: 111644 | K24: 98155 | L24: 97130 | O24: From 10k
B26: depreciation % of rev | C26: =C16/'annual IS'!C8 -> 0.021811143 | D26: =D16/'annual IS'!D8 -> 0.019430155 | E26: =E16/'annual IS'!E8 -> 0.014273314 | F26: =F16/'annual IS'!F8 -> 0.0088036359 | G26: =G16/'annual IS'!G8 -> 0.0038340554 | H26: =G26-$M$26 -> 0.0033340554 | I26: =H26-$M$26 -> 0.0028340554 | J26: =I26-$M$26 -> 0.0023340554 | K26: =J26-$M$26 -> 0.0018340554 | L26: =K26-$M$26 -> 0.0013340554 | M26: 0.0005 | N26: (-)
B27: capex as % rev | C27: =C15/'annual IS'!C8 -> 0.017844241 | D27: =D15/'annual IS'!D8 -> 0.011777053 | E27: =E15/'annual IS'!E8 -> 0.0039118164 | F27: =F15/'annual IS'!F8 -> 0.0016946999 | G27: =G15/'annual IS'!G8 -> 0.0017369938 | H27: =G27+$M$27 -> 0.0019869938 | I27: =H27+$M$27 -> 0.0022369938 | J27: =I27+$M$27 -> 0.0024869938 | K27: =J27+$M$27 -> 0.0027369938 | L27: =K27+$M$27 -> 0.0029869938 | M27: 0.00025 | N27: (+)
A29: x | B29: Liabilities
B31: Current
B32: Accounts Payable - % of COGS | C32: ='Balance Sheet'!C18/'annual IS'!C15 -> 0.0050717078 | D32: ='Balance Sheet'!H18/'annual IS'!D15 -> 0.082742977 | E32: ='Balance Sheet'!M18/'annual IS'!E15 -> 0.03758386 | F32: ='Balance Sheet'!R18/'annual IS'!F15 -> 0.031943229 | G32: ='Balance Sheet'!W18/'annual IS'!G15 -> 0.033989326 | H32: =AVERAGE(E32:G32) -> 0.034505471 | I32: =H32 -> 0.034505471 | J32: =I32 -> 0.034505471 | K32: =J32 -> 0.034505471 | L32: =K32 -> 0.034505471
B34: Accrued compensation - % of OpEx | C34: ='Balance Sheet'!C19/'annual IS'!C25 -> 0.13288052 | D34: ='Balance Sheet'!H19/'annual IS'!D25 -> 0.10522744 | E34: ='Balance Sheet'!M19/'annual IS'!E25 -> 0.094920456 | F34: ='Balance Sheet'!R19/'annual IS'!F25 -> 0.098245725 | G34: ='Balance Sheet'!W19/'annual IS'!G25 -> 0.11274546 | H34: =G34-$M$34 -> 0.10774546 | I34: =H34-$M$34 -> 0.10274546 | J34: =I34-$M$34 -> 0.097745457 | K34: =J34-$M$34 -> 0.092745457 | L34: =K34-$M$34 -> 0.087745457 | M34: 0.005 | N34: (-)
B36: Accrued liabilies - % of OpEx | C36: ='Balance Sheet'!C20/'annual IS'!C25 -> 0.19899297 | D36: ='Balance Sheet'!H20/'annual IS'!D25 -> 0.12856295 | E36: ='Balance Sheet'!M20/'annual IS'!E25 -> 0.09043278 | F36: ='Balance Sheet'!R20/'annual IS'!F25 -> 0.09117555 | G36: ='Balance Sheet'!W20/'annual IS'!G25 -> 0.10185145 | H36: =AVERAGE(D36:G36) -> 0.10300568 | I36: =H36 -> 0.10300568 | J36: =I36 -> 0.10300568 | K36: =J36 -> 0.10300568 | L36: =K36 -> 0.10300568
B38: Current operating lease liabilities - % of OpEx | C38: ='Balance Sheet'!C22/'annual IS'!C25 -> 0.036811602 | D38: ='Balance Sheet'!H22/'annual IS'!D25 -> 0.027170807 | E38: ='Balance Sheet'!M22/'annual IS'!E25 -> 0.02103844 | F38: ='Balance Sheet'!R22/'annual IS'!F25 -> 0.018624069 | G38: ='Balance Sheet'!W22/'annual IS'!G25 -> 0.016263772 | H38: =AVERAGE(C38:G38) -> 0.023981738 | I38: =H38 -> 0.023981738 | J38: =I38 -> 0.023981738 | K38: =J38 -> 0.023981738 | L38: =K38 -> 0.023981738
B40: Long-term
B41: Long-term debt, net - % of rev | C41: ='Balance Sheet'!C25/'annual IS'!C8 -> 1.2598893 | D41: ='Balance Sheet'!H25/'annual IS'!D8 -> 1.2187822 | E41: ='Balance Sheet'!M25/'annual IS'!E8 -> 1.0534843 | F41: ='Balance Sheet'!R25/'annual IS'!F8 -> 0.87533351 | G41: ='Balance Sheet'!W25/'annual IS'!G8 -> 0.88041665 | H41: =G41-$M$41 -> 0.86041665 | I41: =H41-$M$41 -> 0.84041665 | J41: =I41-$M$41 -> 0.82041665 | K41: =J41-$M$41 -> 0.80041665 | L41: =K41-$M$41 -> 0.78041665 | M41: 0.02 | N41: (-)
B43: Operating lease liabilities, non-current - % of OpEx | C43: ='Balance Sheet'!C26/'annual IS'!C25 -> 0.19465016 | D43: ='Balance Sheet'!H26/'annual IS'!D25 -> 0.14562535 | E43: ='Balance Sheet'!M26/'annual IS'!E25 -> 0.12215922 | F43: ='Balance Sheet'!R26/'annual IS'!F25 -> 0.096578194 | G43: ='Balance Sheet'!W26/'annual IS'!G25 -> 0.068657153 | H43: =G43 -> 0.068657153 | I43: =H43-$M$43 -> 0.063657153 | J43: =I43-$M$43 -> 0.058657153 | K43: =J43-$M$43 -> 0.053657153 | L43: =K43-$M$43 -> 0.048657153 | M43: 0.005 | N43: (-)
B45: Other long-term liabilities - % of rev | C45: ='Balance Sheet'!C27/'annual IS'!C8 -> 0.012007034 | D45: ='Balance Sheet'!H27/'annual IS'!D8 -> 0.018749438 | E45: ='Balance Sheet'!M27/'annual IS'!E8 -> 0.014746771 | F45: ='Balance Sheet'!R27/'annual IS'!F8 -> 0.019277962 | G45: ='Balance Sheet'!W27/'annual IS'!G8 -> 0.019138604 | H45: =AVERAGE(C45:G45) -> 0.016783962 | I45: =H45 -> 0.016783962 | J45: =I45 -> 0.016783962 | K45: =J45 -> 0.016783962 | L45: =K45 -> 0.016783962
B47: Deferred Tax Liability - % of rev | C47: ='Balance Sheet'!C28/'annual IS'!C8 -> 0.16321414 | D47: ='Balance Sheet'!H28/'annual IS'!D8 -> 0.13197437 | E47: ='Balance Sheet'!M28/'annual IS'!E8 -> 0.095927116 | F47: ='Balance Sheet'!R28/'annual IS'!F8 -> 0.068698372 | G47: ='Balance Sheet'!W28/'annual IS'!G8 -> 0.046537098 | H47: =G47-$M$47 -> 0.041537098 | I47: =H47-$M$47 -> 0.036537098 | J47: =I47-$M$47 -> 0.031537098 | K47: =J47-$M$47 -> 0.026537098 | L47: =K47-$M$47 -> 0.021537098 | M47: 0.005 | N47: (-)
A49: x | B49: Shareholder's Equity
B50: BOY APIC | C50: 818774 | D50: =C54 -> 1158370 | E50: =D54 -> 1676510 | F50: =E54 -> 1745720 | G50: =F54 -> 1829380 | H50: =G54 -> 1905630 | I50: =H54 -> 2001626.5 | J50: =I54 -> 2105783.4 | K50: =J54 -> 2218288.7 | L50: =K54 -> 2336916.7
B51: Plus: issuance of common stock | C51: =9956+286779 -> 296735 | D51: =8746+456640 -> 465386 | E51: 6594 | F51: 6518 | G51: 9009 | H51: 0 | I51: =H51 -> 0 | J51: =I51 -> 0 | K51: =J51 -> 0 | L51: =K51 -> 0
B52: Plus: SBC | C52: 42863 | D52: 52750 | E52: 62614 | F52: 77151 | G52: 96425 | H52: =H56*'annual IS'!H8 -> 95996.457 | I52: =I56*'annual IS'!I8 -> 104156.97 | J52: =J56*'annual IS'!J8 -> 112505.28 | K52: =K56*'annual IS'!K8 -> 118627.95 | L52: =L56*'annual IS'!L8 -> 125251.8
B53: Less: share repurchases | C53: 0 | D53: 0 | E53: 0 | F53: 0 | G53: 29190 | H53: 0 | I53: 0 | J53: 0 | K53: 0 | L53: 0
B54: EOY: APIC | C54: 1158370 | D54: 1676510 | E54: 1745720 | F54: 1829380 | G54: 1905630 | H54: =H50+H52 -> 2001626.5 | I54: =I50+I52 -> 2105783.4 | J54: =J50+J52 -> 2218288.7 | K54: =K50+K52 -> 2336916.7 | L54: =L50+L52 -> 2462168.5
B56: SBC - % of Revenue | C56: =C52/'annual IS'!C8 -> 0.058430688 | D56: =D52/'annual IS'!D8 -> 0.069723854 | E56: =E52/'annual IS'!E8 -> 0.072659293 | F56: =F52/'annual IS'!F8 -> 0.077182877 | G56: =G52/'annual IS'!G8 -> 0.080369303 | H56: =AVERAGE(C56:G56) -> 0.071673203 | I56: =H56 -> 0.071673203 | J56: =I56 -> 0.071673203 | K56: =J56 -> 0.071673203 | L56: =K56 -> 0.071673203
B58: BOY Retained Earnings | C58: 211514 | D58: =C61 -> 220348 | E58: =D61 -> 176059 | F58: =E61 -> 149916 | G58: =F61 -> 205628 | H58: =G61 -> 209274 | I58: =H61 -> 352943.77 | J58: =I61 -> 525248.3 | K58: =J61 -> 724137.51 | L58: =K61 -> 939045.05
B59: Less: Repurchase of common stock | C59: 0 | D59: 0 | E59: 0 | F59: 0 | G59: 93057 | H59: 0 | I59: 0 | J59: 0 | K59: 0 | L59: 0
B60: Plus: Net Income | C60: 8834 | D60: -44289 | E60: -26143 | F60: 55712 | G60: 96703 | H60: ='annual IS'!H38 -> 143669.77 | I60: ='annual IS'!I38 -> 172304.53 | J60: ='annual IS'!J38 -> 198889.22 | K60: ='annual IS'!K38 -> 214907.54 | L60: ='annual IS'!L38 -> 232893.35
B61: EOY Retained Earnings | C61: 220348 | D61: =D58+D60-D59 -> 176059 | E61: =E58+E60-E59 -> 149916 | F61: =F58+F60-F59 -> 205628 | G61: =G58+G60-G59 -> 209274 | H61: =H58+H60-H59 -> 352943.77 | I61: =I58+I60-I59 -> 525248.3 | J61: =J58+J60-J59 -> 724137.51 | K61: =K58+K60-K59 -> 939045.05 | L61: =L58+L60-L59 -> 1171938.4

Sheet Cash Flow Statement
B1: Statement of Cash Flows - USD($) in thousands | C1: Expected
C2: =2024+1 -> 2025 | D2: =C2+1 -> 2026 | E2: =D2+1 -> 2027 | F2: =E2+1 -> 2028 | G2: =F2+1 -> 2029
A3: x | B3: Operating Activities
B4: Net Income | C4: ='annual IS'!H38 -> 143669.77 | D4: ='annual IS'!I38 -> 172304.53 | E4: ='annual IS'!J38 -> 198889.22 | F4: ='annual IS'!K38 -> 214907.54 | G4: ='annual IS'!L38 -> 232893.35
B5: Plus: Depreciation and Amortization | C5: ='Balance Sheet Build'!H16+'Balance Sheet Build'!H24 -> 150974.51 | D5: ='Balance Sheet Build'!I16+'Balance Sheet Build'!I24 -> 133719.04 | E5: ='Balance Sheet Build'!J16+'Balance Sheet Build'!J24 -> 115307.76 | F5: ='Balance Sheet Build'!K16+'Balance Sheet Build'!K24 -> 101190.59 | G5: ='Balance Sheet Build'!L16+'Balance Sheet Build'!L24 -> 99461.315
B6: Plus: SBC | C6: ='Balance Sheet Build'!H52 -> 95996.457 | D6: ='Balance Sheet Build'!I52 -> 104156.97 | E6: ='Balance Sheet Build'!J52 -> 112505.28 | F6: ='Balance Sheet Build'!K52 -> 118627.95 | G6: ='Balance Sheet Build'!L52 -> 125251.8
A8: x | B8: Changes in operating assets and liabilities:
B9: Accounts receivable, net | C9: ='Balance Sheet'!W6-'Balance Sheet'!AA6 -> -24078.979 | D9: ='Balance Sheet'!AA6-'Balance Sheet'!AB6 -> -12078.427 | E9: ='Balance Sheet'!AB6-'Balance Sheet'!AC6 -> -12356.384 | F9: ='Balance Sheet'!AC6-'Balance Sheet'!AD6 -> -9062.207 | G9: ='Balance Sheet'!AD6-'Balance Sheet'!AE6 -> -9804.0114
B10: Prepaid expenses and Other current assets | C10: ='Balance Sheet'!W7-'Balance Sheet'!AA7 -> 1894.5238 | D10: ='Balance Sheet'!AA7-'Balance Sheet'!AB7 -> -5262.0651 | E10: ='Balance Sheet'!AB7-'Balance Sheet'!AC7 -> -5383.1589 | F10: ='Balance Sheet'!AC7-'Balance Sheet'!AD7 -> -3948.0242 | G10: ='Balance Sheet'!AD7-'Balance Sheet'!AE7 -> -4271.1973
B11: Operating lease right-of-use assets | C11: ='Balance Sheet'!W10-'Balance Sheet'!AA10 -> -1676.0078 | D11: ='Balance Sheet'!AA10-'Balance Sheet'!AB10 -> -180.51454 | E11: ='Balance Sheet'!AB10-'Balance Sheet'!AC10 -> 314.11227 | F11: ='Balance Sheet'!AC10-'Balance Sheet'!AD10 -> 1703.6875 | G11: ='Balance Sheet'!AD10-'Balance Sheet'!AE10 -> 1966.5253
B12: Other assets | C12: ='Balance Sheet'!W13-'Balance Sheet'!AA13 -> -22181.431 | D12: ='Balance Sheet'!AA13-'Balance Sheet'!AB13 -> -9423.2267 | E12: ='Balance Sheet'!AB13-'Balance Sheet'!AC13 -> -9839.5921 | F12: ='Balance Sheet'!AC13-'Balance Sheet'!AD13 -> -7805.7117 | G12: ='Balance Sheet'!AD13-'Balance Sheet'!AE13 -> -8494.0149
B13: Accounts payable | C13: ='Balance Sheet'!AA18-'Balance Sheet'!W18 -> 595.66155 | D13: ='Balance Sheet'!AB18-'Balance Sheet'!AA18 -> 684.78388 | E13: ='Balance Sheet'!AC18-'Balance Sheet'!AB18 -> 728.02966 | F13: ='Balance Sheet'!AD18-'Balance Sheet'!AC18 -> 682.79713 | G13: ='Balance Sheet'!AE18-'Balance Sheet'!AD18 -> 736.51085
B14: Accrued compensation | C14: ='Balance Sheet'!AA19-'Balance Sheet'!W19 -> 2298.365 | D14: ='Balance Sheet'!AB19-'Balance Sheet'!AA19 -> 1957.4216 | E14: ='Balance Sheet'!AC19-'Balance Sheet'!AB19 -> 2029.9951 | F14: ='Balance Sheet'!AD19-'Balance Sheet'!AC19 -> 36.606057 | G14: ='Balance Sheet'!AE19-'Balance Sheet'!AD19 -> -82.008107
B15: Accrued liabilities | C15: ='Balance Sheet'!AA20-'Balance Sheet'!W20 -> 5846.3975 | D15: ='Balance Sheet'!AB20-'Balance Sheet'!AA20 -> 5294.7599 | E15: ='Balance Sheet'!AC20-'Balance Sheet'!AB20 -> 5912.9277 | F15: ='Balance Sheet'!AD20-'Balance Sheet'!AC20 -> 4336.558 | G15: ='Balance Sheet'!AE20-'Balance Sheet'!AD20 -> 4691.5354
B16: Operating lease liabilities | C16: ='Balance Sheet'!AA22-'Balance Sheet'!W22 -> 5941.8781 | D16: ='Balance Sheet'!AB22-'Balance Sheet'!AA22 -> 1232.7237 | E16: ='Balance Sheet'!AC22-'Balance Sheet'!AB22 -> 1376.6453 | F16: ='Balance Sheet'!AD22-'Balance Sheet'!AC22 -> 1009.6356 | G16: ='Balance Sheet'!AE22-'Balance Sheet'!AD22 -> 1092.2812
B17: Operating lease liabilities, non-current | C17: ='Balance Sheet'!AA26-'Balance Sheet'!W26+2 -> 3425.7564 | D17: ='Balance Sheet'!AB26-'Balance Sheet'!AA26+-211.46912-2 -> -265.28803 | E17: ='Balance Sheet'!AC26-'Balance Sheet'!AB26 -> -213.8259 | F17: ='Balance Sheet'!AD26-'Balance Sheet'!AC26 -> -1609.0187 | G17: ='Balance Sheet'!AE26-'Balance Sheet'!AD26 -> -1862.3386
B18: Other long-term liabilities | C18: ='Balance Sheet'!AA27-'Balance Sheet'!W27 -> -482.17758 | D18: ='Balance Sheet'!AB27-'Balance Sheet'!AA27 -> 1910.9754 | E18: ='Balance Sheet'!AC27-'Balance Sheet'!AB27 -> 1954.952 | F18: ='Balance Sheet'!AD27-'Balance Sheet'!AC27 -> 1433.7674 | G18: ='Balance Sheet'!AE27-'Balance Sheet'!AD27 -> 1551.1311
B19: Deferred tax liability | C19: ='Balance Sheet'!AA28-'Balance Sheet'!W28 -> -200.73576 | D19: ='Balance Sheet'!AB28-'Balance Sheet'!X28 -> -4061.5394 | E19: ='Balance Sheet'!AC28-'Balance Sheet'!Y28 -> -37111.283 | F19: ='Balance Sheet'!AD28-'Balance Sheet'!Z28 -> -57650.846 | G19: ='Balance Sheet'!AE28-'Balance Sheet'!AA28 -> -17996.32
A21: x | B21: Cash from operating activities | C21: =SUM(C9:C19,C4:C6) -> 362023.99 | D21: =SUM(D9:D19,D4:D6) -> 389990.14 | E21: =SUM(E9:E19,E4:E6) -> 374114.67 | F21: =SUM(F9:F19,F4:F6) -> 363853.32 | G21: =SUM(G9:G19,G4:G6) -> 425134.57
A23: x | B23: Investing Activities:
B24: Capex | C24: ='Balance Sheet'!W9-'Balance Sheet'!AA9 -> 1804.2049 | D24: ='Balance Sheet'!X9-'Balance Sheet'!AB9 -> 2605.8671 | E24: ='Balance Sheet'!Y9-'Balance Sheet'!AC9 -> 2280.8 | F24: ='Balance Sheet'!Z9-'Balance Sheet'!AD9 -> 1088.3261 | G24: ='Balance Sheet'!AA9-'Balance Sheet'!AE9 -> -3755.4551
B25: Intangible assets, net | C25: ='Balance Sheet'!W11-'Balance Sheet'!AA11 -> 146509 | D25: ='Balance Sheet'!AA11-'Balance Sheet'!AB11 -> 129600.53 | E25: ='Balance Sheet'!AB11-'Balance Sheet'!AC11+30997.67 -> 142641.67 | F25: ='Balance Sheet'!AC11-'Balance Sheet'!AD11+49486 -> 147641 | G25: ='Balance Sheet'!AD11-'Balance Sheet'!AE11+12578 -> 109708
A27: x | B27: Cash from investing activities | C27: =SUM(C24:C25)-C5 -> -2661.3066 | D27: =SUM(D24:D25)-D5 -> -1512.6404 | E27: =SUM(E24:E25)-E5 -> 29614.708 | F27: =SUM(F24:F25)-F5 -> 47538.739 | G27: =SUM(G24:G25)-G5 -> 6491.2295
A29: x | B29: Financing Activities:
B30: Current portion of long-term debt | C30: ='Balance Sheet'!AA21-'Balance Sheet'!W21 -> 0 | D30: 0 | E30: 0 | F30: 0 | G30: ='Balance Sheet'!AE21-'Balance Sheet'!AA21 -> 0
B31: Long term debt | C31: ='Balance Sheet'!AA25-'Balance Sheet'!W25 -> 96109.474 | D31: ='Balance Sheet'!AB25-'Balance Sheet'!AA25 -> 68900.246 | E31: ='Balance Sheet'!AC25-'Balance Sheet'!AB25 -> 66495.574 | F31: ='Balance Sheet'!AD25-'Balance Sheet'!AC25 -> 36981.51 | G31: ='Balance Sheet'!AE25-'Balance Sheet'!AD25 -> 39021.67
A33: x | B33: Cash from financing activities | C33: =SUM(C30:C31) -> 96109.474 | D33: =SUM(D30:D31) -> 68900.246 | E33: =SUM(E30:E31) -> 66495.574 | F33: =SUM(F30:F31) -> 36981.51 | G33: =SUM(G30:G31) -> 39021.67
A35: x | B35: Net Change in Cash | C35: =C33+C27+C21 -> 455472.15 | D35: =D33+D27+D21 -> 457377.75 | E35: =E33+E27+E21 -> 470224.96 | F35: =F33+F27+F21 -> 448373.57 | G35: =G33+G27+G21 -> 470647.47

Sheet IRR
A2: x | B2: IRR | C2: 2024 | D2: =C2+1 -> 2025 | E2: =D2+1 -> 2026 | F2: =E2+1 -> 2027 | G2: =F2+1 -> 2028 | H2: =G2+1 -> 2029
B3: Net Income | C3: ='annual IS'!G38 -> 96703 | D3: ='annual IS'!H38 -> 143669.77 | E3: ='annual IS'!I38 -> 172304.53 | F3: ='annual IS'!J38 -> 198889.22 | G3: ='annual IS'!K38 -> 214907.54 | H3: ='annual IS'!L38 -> 232893.35
B4: Shares | C4: ='annual IS'!G47 -> 88828 | D4: ='annual IS'!H47 -> 88828 | E4: ='annual IS'!I47 -> 88828 | F4: ='annual IS'!J47 -> 88828 | G4: ='annual IS'!K47 -> 88828 | H4: ='annual IS'!L47 -> 88828
B5: EPS | C5: =(C3/C4) -> 1.0886545 | D5: =(D3/D4) -> 1.6173928 | E5: =(E3/E4) -> 1.9397547 | F5: =(F3/F4) -> 2.2390374 | G5: =(G3/G4) -> 2.4193671 | H5: =(H3/H4) -> 2.6218462
B7: Current Price | C7: 96.79
B8: Current P/E | C8: 44.4
B9: Terminal P/E | C9: 35
B11: Implied Price | D11: =$C$9*D5 -> 56.608747 | E11: =$C$9*E5 -> 67.891414 | F11: =$C$9*F5 -> 78.36631 | G11: =$C$9*G5 -> 84.677848 | H11: =$C$9*H5 -> 91.764617
C13: 2024 | D13: =C13+1 -> 2025 | E13: =D13+1 -> 2026 | F13: =E13+1 -> 2027 | G13: =F13+1 -> 2028 | H13: =G13+1 -> 2029 | I13: IRR
B14: Returns Analysis | C14: =-$C$7 -> -96.79 | D14: =D11 -> 56.608747 | I14: =IRR(C14:D14) -> -0.41513847
C15: =-$C$7 -> -96.79 | E15: =E11 -> 67.891414 | I15: =IRR(C15:E15) -> -0.29856995
C16: =-$C$7 -> -96.79 | F16: =F11 -> 78.36631 | I16: =IRR(C16:F16) -> -0.19034704
C17: =-$C$7 -> -96.79 | G17: =G11 -> 84.677848 | I17: =IRR(C17:G17) -> -0.12513846
C18: =-$C$7 -> -96.79 | H18: =H11 -> 91.764617 | I18: =IRR(C18:H18) -> -0.051920482
A21: x | B21: EV/EBITDA IRR | C21: 2024 | D21: =C21+1 -> 2025 | E21: =D21+1 -> 2026 | F21: =E21+1 -> 2027 | G21: =F21+1 -> 2028 | H21: =G21+1 -> 2029
B22: Price per share | C22: =C7 -> 96.79 | D22: =D11 -> 56.608747 | E22: =E11 -> 67.891414 | F22: =F11 -> 78.36631 | G22: =G11 -> 84.677848 | H22: =H11 -> 91.764617
B23: Market cap | C23: =C22*C4 -> 8597662.1 | D23: =D22*D4 -> 5028441.8 | E23: =E22*E4 -> 6030658.6 | F23: =F22*F4 -> 6961122.6 | G23: =G22*G4 -> 7521763.9 | H23: =H22*H4 -> 8151267.4
B24: Net debt | C24: ='Balance Sheet'!W25-'Balance Sheet'!W5 -> 760353 | D24: ='Balance Sheet'!AA25-'Balance Sheet'!AA5 -> 400990.32 | E24: ='Balance Sheet'!AB25-'Balance Sheet'!AB5 -> 12512.819 | F24: ='Balance Sheet'!AC25-'Balance Sheet'!AC5 -> -391216.56 | G24: ='Balance Sheet'!AD25-'Balance Sheet'!AD5 -> -802608.62 | H24: ='Balance Sheet'!AE25-'Balance Sheet'!AE5 -> -1234234.4
B25: EV | C25: =C23-(C24/1000) -> 8596901.8 | D25: =D23-(D24/1000) -> 5028040.8 | E25: =E23-(E24/1000) -> 6030646 | F25: =F23-(F24/1000) -> 6961513.8 | G25: =G23-(G24/1000) -> 7522566.5 | H25: =H23-(H24/1000) -> 8152501.6
B26: Implied EV | C26: =C25-C24 -> 7836548.8 | D26: =D25-D24 -> 4627050.5 | E26: =E25-E24 -> 6018133.2 | F26: =F25-F24 -> 7352730.4 | G26: =G25-G24 -> 8325175.1 | H26: =H25-H24 -> 9386736
B27: EBITDA | C27: ='annual IS'!G27+50573 -> 212907 | D27: ='annual IS'!H27 -> 241113.18 | E27: ='annual IS'!I27+50573 -> 334295.15 | F27: ='annual IS'!J27+50573 -> 372269.67 | G27: ='annual IS'!K27+50573 -> 395806.25 | H27: ='annual IS'!L27+50573 -> 421332.58
B28: Multiple | C28: =C25/C27 -> 40.378671 | D28: =D25/D27 -> 20.853447 | E28: =E25/E27 -> 18.039885 | F28: =F25/F27 -> 18.700191 | G28: =G25/G27 -> 19.005679 | H28: =H25/H27 -> 19.349326
B30: Current Price | C30: =C7 -> 96.79
B32: Implied Price | D32: =D26/D4 -> 52.09 | E32: =E26/E4 -> 67.750408 | F32: =F26/F4 -> 82.774918 | G32: =G26/G4 -> 93.72242 | H32: =H26/H4 -> 105.67317
C34: 2024 | D34: =C34+1 -> 2025 | E34: =D34+1 -> 2026 | F34: =E34+1 -> 2027 | G34: =F34+1 -> 2028 | H34: =G34+1 -> 2029 | I34: IRR
B35: Returns Analysis | C35: =-$C$7 -> -96.79 | D35: =D32 -> 52.09 | I35: =IRR(C35:D35) -> -0.46182457
C36: =-$C$7 -> -96.79 | E36: =E32 -> 67.750408 | I36: =IRR(C36:E36) -> -0.30002678
C37: =-$C$7 -> -96.79 | F37: =F32 -> 82.774918 | I37: =IRR(C37:F37) -> -0.14479886
C38: =-$C$7 -> -96.79 | G38: =G32 -> 93.72242 | I38: =IRR(C38:G38) -> -0.031693149
C39: =-$C$7 -> -96.79 | H39: =H32 -> 105.67317 | I39: =IRR(C39:H39) -> 0.091777728

Sheet DCF
B2: HQY DCF | C2: Expected | J2: Terminal Assumption
C3: 2025E | D3: 2026E | E3: 2027E | F3: 2028E | G3: 2029E | J3: Valuation date | K3: 46003
B4: Net Change in Cash | C4: ='Cash Flow Statement'!C35 -> 455472.15 | D4: ='Cash Flow Statement'!D35 -> 457377.75 | E4: ='Cash Flow Statement'!E35 -> 470224.96 | F4: ='Cash Flow Statement'!F35 -> 448373.57 | G4: ='Cash Flow Statement'!G35 -> 470647.47 | J4: FY End | K4: 46053
B5: Dividends | C5: 0 | D5: 0 | E5: 0 | F5: 0 | G5: 0 | J5: Terminal Growth Rate | K5: 0.02
B6: FCFE | C6: =C4/1000 -> 455.47215 | D6: =D4/1000 -> 457.37775 | E6: =E4/1000 -> 470.22496 | F6: =F4/1000 -> 448.37357 | G6: =G4/1000 -> 470.64747
J7: Capital Asset Pricing Model
J8: Cost of Equity
J9: Risk Free rate | K9: 0.0419
B10: Discount Factor | C10: =1/(1+$K$12)^1 -> 0.9518751 | D10: =1/(1+$K$12)^2 -> 0.9060662 | E10: =1/(1+$K$12)^3 -> 0.86246186 | F10: =1/(1+$K$12)^4 -> 0.82095597 | G10: =1/(1+$K$12)^5 -> 0.78144754 | J10: Beta | K10: 0.18
B11: PV of FCFE | C11: =C6*C10 -> 433.5526 | D11: =D6*D10 -> 414.41452 | E11: =E6*E10 -> 405.55109 | F11: =F6*F10 -> 368.09496 | G11: =G6*G10 -> 367.78631 | J11: Expected Market Return | K11: 0.09
J12: Ke | K12: =K9+(0.18*(K11-K9)) -> 0.050558
B17: Current Valuation
B18: Terminal Valuation | C18: =(G6*(1+K5))/(K12-K5) -> 15709.811
B19: PV of TV | C19: =C18*G10 -> 12276.393
B20: PV of Equity | C20: =SUM(C11:G11,C19) -> 14265.793
B21: Diluted Shares | C21: ='annual IS'!G47 -> 88828
B22: share price | C22: =C20/(C21/1000) -> 160.60018

Sheet KPIs
C6: Key Metrics
C7: Revenue | D7: $1.199 B | E7: 1199774
C8: Gross Margin | D8: ='[1]quarterly IS'!W16 -> 0.64783784
C9: EBITDA | D9: $212.91 M | E9: 212907
C10: EPS | D10: 1.11
C11: EV/EBITDA | D11: =D22/E9 -> 43.953534
C13: Stock Details
C14: Current Price | D14: 96.79
C15: YTD% | D15: -0.0002
C16: 52wk (High/low) | D16: $117/$74
C17: # of Shares | D17: 88.8M
C22: EV | D22: =(([1]IRR!C7*'[1]annual IS'!G46)+'[1]Balance Sheet'!W25-'[1]Balance Sheet'!W5) -> 9358015.1
